{"v":"5.1.8","fr":60,"ip":0,"op":241,"w":960,"h":720,"nm":"表扬榜","ddd":0,"assets":[{"id":"image_0","w":382,"h":76,"u":"images/","p":"img_0.png"},{"id":"image_1","w":541,"h":136,"u":"images/","p":"img_1.png"},{"id":"image_2","w":697,"h":605,"u":"images/","p":"img_2.png"},{"id":"image_3","w":63,"h":63,"u":"images/","p":"img_3.png"},{"id":"image_4","w":63,"h":63,"u":"images/","p":"img_4.png"},{"id":"image_5","w":42,"h":43,"u":"images/","p":"img_5.png"},{"id":"image_6","w":42,"h":43,"u":"images/","p":"img_6.png"},{"id":"image_7","w":12,"h":12,"u":"images/","p":"img_7.png"},{"id":"image_8","w":12,"h":12,"u":"images/","p":"img_8.png"},{"id":"image_9","w":8,"h":8,"u":"images/","p":"img_9.png"},{"id":"image_10","w":8,"h":8,"u":"images/","p":"img_10.png"},{"id":"image_11","w":150,"h":133,"u":"images/","p":"img_11.png"},{"id":"image_12","w":162,"h":161,"u":"images/","p":"img_12.png"},{"id":"image_13","w":128,"h":80,"u":"images/","p":"img_13.png"},{"id":"image_14","w":169,"h":101,"u":"images/","p":"img_14.png"},{"id":"image_15","w":1104,"h":381,"u":"images/","p":"img_15.png"},{"id":"image_16","w":227,"h":230,"u":"images/","p":"img_16.png"},{"id":"image_17","w":258,"h":205,"u":"images/","p":"img_17.png"},{"id":"image_18","w":429,"h":357,"u":"images/","p":"img_18.png"},{"id":"image_19","w":463,"h":393,"u":"images/","p":"img_19.png"},{"id":"comp_0","layers":[{"ddd":0,"ind":1,"ty":2,"nm":"小安老师班的最牛学神","refId":"image_0","sr":1,"ks":{"o":{"a":0,"k":100,"ix":11},"r":{"a":0,"k":0,"ix":10},"p":{"a":0,"k":[482,164,0],"ix":2},"a":{"a":0,"k":[191,38,0],"ix":1},"s":{"a":0,"k":[100,100,100],"ix":6}},"ao":0,"ip":0,"op":602,"st":0,"bm":0},{"ddd":0,"ind":2,"ty":2,"nm":"1.png","cl":"png","refId":"image_1","sr":1,"ks":{"o":{"a":0,"k":100,"ix":11},"r":{"a":0,"k":0,"ix":10},"p":{"a":0,"k":[480,164,0],"ix":2},"a":{"a":0,"k":[270.5,68,0],"ix":1},"s":{"a":0,"k":[100,100,100],"ix":6}},"ao":0,"ip":0,"op":602,"st":0,"bm":0},{"ddd":0,"ind":3,"ty":2,"nm":"2.png","cl":"png","refId":"image_2","sr":1,"ks":{"o":{"a":0,"k":100,"ix":11},"r":{"a":0,"k":0,"ix":10},"p":{"a":0,"k":[480,349,0],"ix":2},"a":{"a":0,"k":[348.5,302.5,0],"ix":1},"s":{"a":0,"k":[100,100,100],"ix":6}},"ao":0,"ip":0,"op":602,"st":0,"bm":0},{"ddd":0,"ind":4,"ty":2,"nm":"1","refId":"image_3","sr":1,"ks":{"o":{"a":0,"k":100,"ix":11},"r":{"a":1,"k":[{"i":{"x":[0.667],"y":[1]},"o":{"x":[0.333],"y":[0]},"n":["0p667_1_0p333_0"],"t":35,"s":[0],"e":[-15]},{"i":{"x":[0.667],"y":[1]},"o":{"x":[0.333],"y":[0]},"n":["0p667_1_0p333_0"],"t":45,"s":[-15],"e":[0]},{"i":{"x":[0.667],"y":[1]},"o":{"x":[0.167],"y":[0]},"n":["0p667_1_0p167_0"],"t":55,"s":[0],"e":[-15]},{"i":{"x":[0.667],"y":[1]},"o":{"x":[0.333],"y":[0]},"n":["0p667_1_0p333_0"],"t":65,"s":[-15],"e":[0]},{"i":{"x":[0.833],"y":[1]},"o":{"x":[0.167],"y":[0]},"n":["0p833_1_0p167_0"],"t":75,"s":[0],"e":[0]},{"t":180}],"ix":10,"x":"var $bm_rt;\n$bm_rt = loopOut('cycle', 0);"},"p":{"a":0,"k":[520,79,0],"ix":2},"a":{"a":0,"k":[0,63,0],"ix":1},"s":{"a":0,"k":[100,100,100],"ix":6}},"ao":0,"ip":0,"op":602,"st":0,"bm":0},{"ddd":0,"ind":5,"ty":2,"nm":"2","refId":"image_4","sr":1,"ks":{"o":{"a":0,"k":100,"ix":11},"r":{"a":1,"k":[{"i":{"x":[0.667],"y":[1]},"o":{"x":[0.333],"y":[0]},"n":["0p667_1_0p333_0"],"t":35,"s":[0],"e":[15]},{"i":{"x":[0.667],"y":[1]},"o":{"x":[0.333],"y":[0]},"n":["0p667_1_0p333_0"],"t":45,"s":[15],"e":[0]},{"i":{"x":[0.667],"y":[1]},"o":{"x":[0.167],"y":[0]},"n":["0p667_1_0p167_0"],"t":55,"s":[0],"e":[15]},{"i":{"x":[0.667],"y":[1]},"o":{"x":[0.333],"y":[0]},"n":["0p667_1_0p333_0"],"t":65,"s":[15],"e":[0]},{"i":{"x":[0.833],"y":[1]},"o":{"x":[0.167],"y":[0]},"n":["0p833_1_0p167_0"],"t":75,"s":[0],"e":[0]},{"t":180}],"ix":10,"x":"var $bm_rt;\n$bm_rt = loopOut('cycle', 0);"},"p":{"a":0,"k":[448,79,0],"ix":2},"a":{"a":0,"k":[63,63,0],"ix":1},"s":{"a":0,"k":[100,100,100],"ix":6}},"ao":0,"ip":0,"op":602,"st":0,"bm":0}]}],"layers":[{"ddd":0,"ind":9,"ty":0,"nm":"Pre-comp 13","refId":"comp_0","sr":1,"ks":{"o":{"a":0,"k":100,"ix":11},"r":{"a":0,"k":0,"ix":10},"p":{"a":0,"k":[480,360,0],"ix":2},"a":{"a":0,"k":[480,360,0],"ix":1},"s":{"a":1,"k":[{"i":{"x":[0.4,0.4,0.4],"y":[1,1,1]},"o":{"x":[0.001,0.001,0.001],"y":[0,0,0]},"n":["0p4_1_0p001_0","0p4_1_0p001_0","0p4_1_0p001_0"],"t":60,"s":[0,0,100],"e":[113.1,113.1,100]},{"i":{"x":[0.6,0.6,0.6],"y":[1,1,1]},"o":{"x":[0.4,0.4,0.4],"y":[0,0,0]},"n":["0p6_1_0p4_0","0p6_1_0p4_0","0p6_1_0p4_0"],"t":80.699,"s":[113.1,113.1,100],"e":[93.301,93.301,100]},{"i":{"x":[0.6,0.6,0.6],"y":[1,1,1]},"o":{"x":[0.4,0.4,0.4],"y":[0,0,0]},"n":["0p6_1_0p4_0","0p6_1_0p4_0","0p6_1_0p4_0"],"t":108.301,"s":[93.301,93.301,100],"e":[101.1,101.1,100]},{"i":{"x":[0.6,0.6,0.6],"y":[1,1,1]},"o":{"x":[0.4,0.4,0.4],"y":[0,0,0]},"n":["0p6_1_0p4_0","0p6_1_0p4_0","0p6_1_0p4_0"],"t":138,"s":[101.1,101.1,100],"e":[100,100,100]},{"t":160}],"ix":6}},"ao":0,"w":960,"h":720,"ip":60,"op":241,"st":60,"bm":0},{"ddd":0,"ind":10,"ty":2,"nm":"星1","refId":"image_5","sr":1,"ks":{"o":{"a":0,"k":100,"ix":11},"r":{"a":0,"k":0,"ix":10},"p":{"a":0,"k":[783,62.5,0],"ix":2},"a":{"a":0,"k":[21,21.5,0],"ix":1},"s":{"a":1,"k":[{"i":{"x":[0.833,0.833,0.833],"y":[0.833,0.833,0.833]},"o":{"x":[0.167,0.167,0.167],"y":[0.167,0.167,0.167]},"n":["0p833_0p833_0p167_0p167","0p833_0p833_0p167_0p167","0p833_0p833_0p167_0p167"],"t":15,"s":[0,0,100],"e":[100,100,100]},{"i":{"x":[0.833,0.833,0.833],"y":[0.833,0.833,0.833]},"o":{"x":[0.167,0.167,0.167],"y":[0.167,0.167,0.167]},"n":["0p833_0p833_0p167_0p167","0p833_0p833_0p167_0p167","0p833_0p833_0p167_0p167"],"t":125.365,"s":[100,100,100],"e":[0,0,100]},{"i":{"x":[0.833,0.833,0.833],"y":[0.833,0.833,0.833]},"o":{"x":[0.167,0.167,0.167],"y":[0.167,0.167,0.167]},"n":["0p833_0p833_0p167_0p167","0p833_0p833_0p167_0p167","0p833_0p833_0p167_0p167"],"t":240,"s":[0,0,100],"e":[100,100,100]},{"i":{"x":[0.833,0.833,0.833],"y":[0.833,0.833,0.833]},"o":{"x":[0.167,0.167,0.167],"y":[0.167,0.167,0.167]},"n":["0p833_0p833_0p167_0p167","0p833_0p833_0p167_0p167","0p833_0p833_0p167_0p167"],"t":350.365,"s":[100,100,100],"e":[0,0,100]},{"i":{"x":[0.833,0.833,0.833],"y":[0.833,0.833,0.833]},"o":{"x":[0.167,0.167,0.167],"y":[0.167,0.167,0.167]},"n":["0p833_0p833_0p167_0p167","0p833_0p833_0p167_0p167","0p833_0p833_0p167_0p167"],"t":465,"s":[0,0,100],"e":[100,100,100]},{"i":{"x":[0.833,0.833,0.833],"y":[0.833,0.833,0.833]},"o":{"x":[0.167,0.167,0.167],"y":[0.167,0.167,0.167]},"n":["0p833_0p833_0p167_0p167","0p833_0p833_0p167_0p167","0p833_0p833_0p167_0p167"],"t":575.365,"s":[100,100,100],"e":[0,0,100]},{"t":690}],"ix":6,"x":"var $bm_rt;\n$bm_rt = loopOut('cycle', 0);"}},"ao":0,"ip":15,"op":241,"st":15,"bm":0},{"ddd":0,"ind":11,"ty":2,"nm":"星2","refId":"image_6","sr":1,"ks":{"o":{"a":0,"k":100,"ix":11},"r":{"a":0,"k":0,"ix":10},"p":{"a":0,"k":[68,344.5,0],"ix":2},"a":{"a":0,"k":[21,21.5,0],"ix":1},"s":{"a":1,"k":[{"i":{"x":[0.833,0.833,0.833],"y":[0.833,0.833,0.833]},"o":{"x":[0.167,0.167,0.167],"y":[0.167,0.167,0.167]},"n":["0p833_0p833_0p167_0p167","0p833_0p833_0p167_0p167","0p833_0p833_0p167_0p167"],"t":5,"s":[0,0,100],"e":[100,100,100]},{"i":{"x":[0.833,0.833,0.833],"y":[0.833,0.833,0.833]},"o":{"x":[0.167,0.167,0.167],"y":[0.167,0.167,0.167]},"n":["0p833_0p833_0p167_0p167","0p833_0p833_0p167_0p167","0p833_0p833_0p167_0p167"],"t":111.037,"s":[100,100,100],"e":[0,0,100]},{"i":{"x":[0.833,0.833,0.833],"y":[0.833,0.833,0.833]},"o":{"x":[0.167,0.167,0.167],"y":[0.167,0.167,0.167]},"n":["0p833_0p833_0p167_0p167","0p833_0p833_0p167_0p167","0p833_0p833_0p167_0p167"],"t":225.67,"s":[0,0,100],"e":[0,0,100]},{"i":{"x":[0.833,0.833,0.833],"y":[0.833,0.833,0.833]},"o":{"x":[0.167,0.167,0.167],"y":[0.167,0.167,0.167]},"n":["0p833_0p833_0p167_0p167","0p833_0p833_0p167_0p167","0p833_0p833_0p167_0p167"],"t":226,"s":[0,0,100],"e":[100,100,100]},{"i":{"x":[0.833,0.833,0.833],"y":[0.833,0.833,0.833]},"o":{"x":[0.167,0.167,0.167],"y":[0.167,0.167,0.167]},"n":["0p833_0p833_0p167_0p167","0p833_0p833_0p167_0p167","0p833_0p833_0p167_0p167"],"t":336.365,"s":[100,100,100],"e":[0,0,100]},{"i":{"x":[0.833,0.833,0.833],"y":[0.833,0.833,0.833]},"o":{"x":[0.167,0.167,0.167],"y":[0.167,0.167,0.167]},"n":["0p833_0p833_0p167_0p167","0p833_0p833_0p167_0p167","0p833_0p833_0p167_0p167"],"t":451,"s":[0,0,100],"e":[100,100,100]},{"i":{"x":[0.833,0.833,0.833],"y":[0.833,0.833,0.833]},"o":{"x":[0.167,0.167,0.167],"y":[0.167,0.167,0.167]},"n":["0p833_0p833_0p167_0p167","0p833_0p833_0p167_0p167","0p833_0p833_0p167_0p167"],"t":561.365,"s":[100,100,100],"e":[0,0,100]},{"t":676}],"ix":6,"x":"var $bm_rt;\n$bm_rt = loopOut('cycle', 0);"}},"ao":0,"ip":5,"op":241,"st":5,"bm":0},{"ddd":0,"ind":12,"ty":2,"nm":"点1","refId":"image_7","sr":1,"ks":{"o":{"a":0,"k":100,"ix":11},"r":{"a":0,"k":0,"ix":10},"p":{"a":0,"k":[660,72,0],"ix":2},"a":{"a":0,"k":[6,6,0],"ix":1},"s":{"a":1,"k":[{"i":{"x":[0.833,0.833,0.833],"y":[0.833,0.833,0.833]},"o":{"x":[0.167,0.167,0.167],"y":[0.167,0.167,0.167]},"n":["0p833_0p833_0p167_0p167","0p833_0p833_0p167_0p167","0p833_0p833_0p167_0p167"],"t":5,"s":[0,0,100],"e":[100,100,100]},{"i":{"x":[0.833,0.833,0.833],"y":[0.833,0.833,0.833]},"o":{"x":[0.167,0.167,0.167],"y":[0.167,0.167,0.167]},"n":["0p833_0p833_0p167_0p167","0p833_0p833_0p167_0p167","0p833_0p833_0p167_0p167"],"t":45,"s":[100,100,100],"e":[0,0,100]},{"i":{"x":[0.833,0.833,0.833],"y":[0.833,0.833,0.833]},"o":{"x":[0.167,0.167,0.167],"y":[0.167,0.167,0.167]},"n":["0p833_0p833_0p167_0p167","0p833_0p833_0p167_0p167","0p833_0p833_0p167_0p167"],"t":85,"s":[0,0,100],"e":[100,100,100]},{"i":{"x":[0.833,0.833,0.833],"y":[0.833,0.833,0.833]},"o":{"x":[0.167,0.167,0.167],"y":[0.167,0.167,0.167]},"n":["0p833_0p833_0p167_0p167","0p833_0p833_0p167_0p167","0p833_0p833_0p167_0p167"],"t":125,"s":[100,100,100],"e":[0,0,100]},{"i":{"x":[0.833,0.833,0.833],"y":[0.833,0.833,0.833]},"o":{"x":[0.167,0.167,0.167],"y":[0.167,0.167,0.167]},"n":["0p833_0p833_0p167_0p167","0p833_0p833_0p167_0p167","0p833_0p833_0p167_0p167"],"t":165,"s":[0,0,100],"e":[100,100,100]},{"i":{"x":[0.833,0.833,0.833],"y":[0.833,0.833,0.833]},"o":{"x":[0.167,0.167,0.167],"y":[0.167,0.167,0.167]},"n":["0p833_0p833_0p167_0p167","0p833_0p833_0p167_0p167","0p833_0p833_0p167_0p167"],"t":205,"s":[100,100,100],"e":[0,0,100]},{"i":{"x":[0.833,0.833,0.833],"y":[0.833,0.833,0.833]},"o":{"x":[0.167,0.167,0.167],"y":[0.167,0.167,0.167]},"n":["0p833_0p833_0p167_0p167","0p833_0p833_0p167_0p167","0p833_0p833_0p167_0p167"],"t":245,"s":[0,0,100],"e":[100,100,100]},{"i":{"x":[0.833,0.833,0.833],"y":[0.833,0.833,0.833]},"o":{"x":[0.167,0.167,0.167],"y":[0.167,0.167,0.167]},"n":["0p833_0p833_0p167_0p167","0p833_0p833_0p167_0p167","0p833_0p833_0p167_0p167"],"t":285,"s":[100,100,100],"e":[0,0,100]},{"i":{"x":[0.833,0.833,0.833],"y":[0.833,0.833,0.833]},"o":{"x":[0.167,0.167,0.167],"y":[0.167,0.167,0.167]},"n":["0p833_0p833_0p167_0p167","0p833_0p833_0p167_0p167","0p833_0p833_0p167_0p167"],"t":325,"s":[0,0,100],"e":[100,100,100]},{"i":{"x":[0.833,0.833,0.833],"y":[0.833,0.833,0.833]},"o":{"x":[0.167,0.167,0.167],"y":[0.167,0.167,0.167]},"n":["0p833_0p833_0p167_0p167","0p833_0p833_0p167_0p167","0p833_0p833_0p167_0p167"],"t":365,"s":[100,100,100],"e":[0,0,100]},{"i":{"x":[0.833,0.833,0.833],"y":[0.833,0.833,0.833]},"o":{"x":[0.167,0.167,0.167],"y":[0.167,0.167,0.167]},"n":["0p833_0p833_0p167_0p167","0p833_0p833_0p167_0p167","0p833_0p833_0p167_0p167"],"t":405,"s":[0,0,100],"e":[100,100,100]},{"i":{"x":[0.833,0.833,0.833],"y":[0.833,0.833,0.833]},"o":{"x":[0.167,0.167,0.167],"y":[0.167,0.167,0.167]},"n":["0p833_0p833_0p167_0p167","0p833_0p833_0p167_0p167","0p833_0p833_0p167_0p167"],"t":445,"s":[100,100,100],"e":[0,0,100]},{"i":{"x":[0.833,0.833,0.833],"y":[0.833,0.833,0.833]},"o":{"x":[0.167,0.167,0.167],"y":[0.167,0.167,0.167]},"n":["0p833_0p833_0p167_0p167","0p833_0p833_0p167_0p167","0p833_0p833_0p167_0p167"],"t":485,"s":[0,0,100],"e":[100,100,100]},{"i":{"x":[0.833,0.833,0.833],"y":[0.833,0.833,0.833]},"o":{"x":[0.167,0.167,0.167],"y":[0.167,0.167,0.167]},"n":["0p833_0p833_0p167_0p167","0p833_0p833_0p167_0p167","0p833_0p833_0p167_0p167"],"t":525,"s":[100,100,100],"e":[0,0,100]},{"i":{"x":[0.833,0.833,0.833],"y":[0.833,0.833,0.833]},"o":{"x":[0.167,0.167,0.167],"y":[0.167,0.167,0.167]},"n":["0p833_0p833_0p167_0p167","0p833_0p833_0p167_0p167","0p833_0p833_0p167_0p167"],"t":565,"s":[0,0,100],"e":[100,100,100]},{"i":{"x":[0.833,0.833,0.833],"y":[0.833,0.833,0.833]},"o":{"x":[0.167,0.167,0.167],"y":[0.167,0.167,0.167]},"n":["0p833_0p833_0p167_0p167","0p833_0p833_0p167_0p167","0p833_0p833_0p167_0p167"],"t":605,"s":[100,100,100],"e":[0,0,100]},{"i":{"x":[0.833,0.833,0.833],"y":[0.833,0.833,0.833]},"o":{"x":[0.167,0.167,0.167],"y":[0.167,0.167,0.167]},"n":["0p833_0p833_0p167_0p167","0p833_0p833_0p167_0p167","0p833_0p833_0p167_0p167"],"t":645,"s":[0,0,100],"e":[100,100,100]},{"i":{"x":[0.833,0.833,0.833],"y":[0.833,0.833,0.833]},"o":{"x":[0.167,0.167,0.167],"y":[0.167,0.167,0.167]},"n":["0p833_0p833_0p167_0p167","0p833_0p833_0p167_0p167","0p833_0p833_0p167_0p167"],"t":685,"s":[100,100,100],"e":[0,0,100]},{"i":{"x":[0.833,0.833,0.833],"y":[0.833,0.833,0.833]},"o":{"x":[0.167,0.167,0.167],"y":[0.167,0.167,0.167]},"n":["0p833_0p833_0p167_0p167","0p833_0p833_0p167_0p167","0p833_0p833_0p167_0p167"],"t":725,"s":[0,0,100],"e":[100,100,100]},{"i":{"x":[0.833,0.833,0.833],"y":[0.833,0.833,0.833]},"o":{"x":[0.167,0.167,0.167],"y":[0.167,0.167,0.167]},"n":["0p833_0p833_0p167_0p167","0p833_0p833_0p167_0p167","0p833_0p833_0p167_0p167"],"t":765,"s":[100,100,100],"e":[0,0,100]},{"i":{"x":[0.833,0.833,0.833],"y":[0.833,0.833,0.833]},"o":{"x":[0.167,0.167,0.167],"y":[0.167,0.167,0.167]},"n":["0p833_0p833_0p167_0p167","0p833_0p833_0p167_0p167","0p833_0p833_0p167_0p167"],"t":805,"s":[0,0,100],"e":[100,100,100]},{"i":{"x":[0.833,0.833,0.833],"y":[0.833,0.833,0.833]},"o":{"x":[0.167,0.167,0.167],"y":[0.167,0.167,0.167]},"n":["0p833_0p833_0p167_0p167","0p833_0p833_0p167_0p167","0p833_0p833_0p167_0p167"],"t":845,"s":[100,100,100],"e":[0,0,100]},{"i":{"x":[0.833,0.833,0.833],"y":[0.833,0.833,0.833]},"o":{"x":[0.167,0.167,0.167],"y":[0.167,0.167,0.167]},"n":["0p833_0p833_0p167_0p167","0p833_0p833_0p167_0p167","0p833_0p833_0p167_0p167"],"t":885,"s":[0,0,100],"e":[100,100,100]},{"i":{"x":[0.833,0.833,0.833],"y":[0.833,0.833,0.833]},"o":{"x":[0.167,0.167,0.167],"y":[0.167,0.167,0.167]},"n":["0p833_0p833_0p167_0p167","0p833_0p833_0p167_0p167","0p833_0p833_0p167_0p167"],"t":925,"s":[100,100,100],"e":[0,0,100]},{"t":965}],"ix":6,"x":"var $bm_rt;\n$bm_rt = loopOut('cycle', 0);"}},"ao":0,"ip":5,"op":241,"st":5,"bm":0},{"ddd":0,"ind":13,"ty":2,"nm":"点2","refId":"image_8","sr":1,"ks":{"o":{"a":0,"k":100,"ix":11},"r":{"a":0,"k":0,"ix":10},"p":{"a":0,"k":[15,108,0],"ix":2},"a":{"a":0,"k":[6,6,0],"ix":1},"s":{"a":1,"k":[{"i":{"x":[0.833,0.833,0.833],"y":[0.833,0.833,0.833]},"o":{"x":[0.167,0.167,0.167],"y":[0.167,0.167,0.167]},"n":["0p833_0p833_0p167_0p167","0p833_0p833_0p167_0p167","0p833_0p833_0p167_0p167"],"t":10,"s":[0,0,100],"e":[100,100,100]},{"i":{"x":[0.833,0.833,0.833],"y":[0.833,0.833,0.833]},"o":{"x":[0.167,0.167,0.167],"y":[0.167,0.167,0.167]},"n":["0p833_0p833_0p167_0p167","0p833_0p833_0p167_0p167","0p833_0p833_0p167_0p167"],"t":50,"s":[100,100,100],"e":[0,0,100]},{"i":{"x":[0.833,0.833,0.833],"y":[0.833,0.833,0.833]},"o":{"x":[0.167,0.167,0.167],"y":[0.167,0.167,0.167]},"n":["0p833_0p833_0p167_0p167","0p833_0p833_0p167_0p167","0p833_0p833_0p167_0p167"],"t":90,"s":[0,0,100],"e":[100,100,100]},{"i":{"x":[0.833,0.833,0.833],"y":[0.833,0.833,0.833]},"o":{"x":[0.167,0.167,0.167],"y":[0.167,0.167,0.167]},"n":["0p833_0p833_0p167_0p167","0p833_0p833_0p167_0p167","0p833_0p833_0p167_0p167"],"t":130,"s":[100,100,100],"e":[0,0,100]},{"i":{"x":[0.833,0.833,0.833],"y":[0.833,0.833,0.833]},"o":{"x":[0.167,0.167,0.167],"y":[0.167,0.167,0.167]},"n":["0p833_0p833_0p167_0p167","0p833_0p833_0p167_0p167","0p833_0p833_0p167_0p167"],"t":170,"s":[0,0,100],"e":[100,100,100]},{"i":{"x":[0.833,0.833,0.833],"y":[0.833,0.833,0.833]},"o":{"x":[0.167,0.167,0.167],"y":[0.167,0.167,0.167]},"n":["0p833_0p833_0p167_0p167","0p833_0p833_0p167_0p167","0p833_0p833_0p167_0p167"],"t":210,"s":[100,100,100],"e":[0,0,100]},{"i":{"x":[0.833,0.833,0.833],"y":[0.833,0.833,0.833]},"o":{"x":[0.167,0.167,0.167],"y":[0.167,0.167,0.167]},"n":["0p833_0p833_0p167_0p167","0p833_0p833_0p167_0p167","0p833_0p833_0p167_0p167"],"t":250,"s":[0,0,100],"e":[100,100,100]},{"i":{"x":[0.833,0.833,0.833],"y":[0.833,0.833,0.833]},"o":{"x":[0.167,0.167,0.167],"y":[0.167,0.167,0.167]},"n":["0p833_0p833_0p167_0p167","0p833_0p833_0p167_0p167","0p833_0p833_0p167_0p167"],"t":290,"s":[100,100,100],"e":[0,0,100]},{"i":{"x":[0.833,0.833,0.833],"y":[0.833,0.833,0.833]},"o":{"x":[0.167,0.167,0.167],"y":[0.167,0.167,0.167]},"n":["0p833_0p833_0p167_0p167","0p833_0p833_0p167_0p167","0p833_0p833_0p167_0p167"],"t":330,"s":[0,0,100],"e":[100,100,100]},{"i":{"x":[0.833,0.833,0.833],"y":[0.833,0.833,0.833]},"o":{"x":[0.167,0.167,0.167],"y":[0.167,0.167,0.167]},"n":["0p833_0p833_0p167_0p167","0p833_0p833_0p167_0p167","0p833_0p833_0p167_0p167"],"t":370,"s":[100,100,100],"e":[0,0,100]},{"i":{"x":[0.833,0.833,0.833],"y":[0.833,0.833,0.833]},"o":{"x":[0.167,0.167,0.167],"y":[0.167,0.167,0.167]},"n":["0p833_0p833_0p167_0p167","0p833_0p833_0p167_0p167","0p833_0p833_0p167_0p167"],"t":410,"s":[0,0,100],"e":[100,100,100]},{"i":{"x":[0.833,0.833,0.833],"y":[0.833,0.833,0.833]},"o":{"x":[0.167,0.167,0.167],"y":[0.167,0.167,0.167]},"n":["0p833_0p833_0p167_0p167","0p833_0p833_0p167_0p167","0p833_0p833_0p167_0p167"],"t":450,"s":[100,100,100],"e":[0,0,100]},{"i":{"x":[0.833,0.833,0.833],"y":[0.833,0.833,0.833]},"o":{"x":[0.167,0.167,0.167],"y":[0.167,0.167,0.167]},"n":["0p833_0p833_0p167_0p167","0p833_0p833_0p167_0p167","0p833_0p833_0p167_0p167"],"t":490,"s":[0,0,100],"e":[100,100,100]},{"i":{"x":[0.833,0.833,0.833],"y":[0.833,0.833,0.833]},"o":{"x":[0.167,0.167,0.167],"y":[0.167,0.167,0.167]},"n":["0p833_0p833_0p167_0p167","0p833_0p833_0p167_0p167","0p833_0p833_0p167_0p167"],"t":530,"s":[100,100,100],"e":[0,0,100]},{"t":570}],"ix":6,"x":"var $bm_rt;\n$bm_rt = loopOut('cycle', 0);"}},"ao":0,"ip":10,"op":241,"st":10,"bm":0},{"ddd":0,"ind":14,"ty":2,"nm":"点3","refId":"image_9","sr":1,"ks":{"o":{"a":0,"k":100,"ix":11},"r":{"a":0,"k":0,"ix":10},"p":{"a":0,"k":[31,257,0],"ix":2},"a":{"a":0,"k":[4,4,0],"ix":1},"s":{"a":1,"k":[{"i":{"x":[0.833,0.833,0.833],"y":[0.833,0.833,0.833]},"o":{"x":[0.167,0.167,0.167],"y":[0.167,0.167,0.167]},"n":["0p833_0p833_0p167_0p167","0p833_0p833_0p167_0p167","0p833_0p833_0p167_0p167"],"t":15,"s":[0,0,100],"e":[100,100,100]},{"i":{"x":[0.833,0.833,0.833],"y":[0.833,0.833,0.833]},"o":{"x":[0.167,0.167,0.167],"y":[0.167,0.167,0.167]},"n":["0p833_0p833_0p167_0p167","0p833_0p833_0p167_0p167","0p833_0p833_0p167_0p167"],"t":55,"s":[100,100,100],"e":[0,0,100]},{"i":{"x":[0.833,0.833,0.833],"y":[0.833,0.833,0.833]},"o":{"x":[0.167,0.167,0.167],"y":[0.167,0.167,0.167]},"n":["0p833_0p833_0p167_0p167","0p833_0p833_0p167_0p167","0p833_0p833_0p167_0p167"],"t":95,"s":[0,0,100],"e":[100,100,100]},{"i":{"x":[0.833,0.833,0.833],"y":[0.833,0.833,0.833]},"o":{"x":[0.167,0.167,0.167],"y":[0.167,0.167,0.167]},"n":["0p833_0p833_0p167_0p167","0p833_0p833_0p167_0p167","0p833_0p833_0p167_0p167"],"t":135,"s":[100,100,100],"e":[0,0,100]},{"i":{"x":[0.833,0.833,0.833],"y":[0.833,0.833,0.833]},"o":{"x":[0.167,0.167,0.167],"y":[0.167,0.167,0.167]},"n":["0p833_0p833_0p167_0p167","0p833_0p833_0p167_0p167","0p833_0p833_0p167_0p167"],"t":175,"s":[0,0,100],"e":[100,100,100]},{"i":{"x":[0.833,0.833,0.833],"y":[0.833,0.833,0.833]},"o":{"x":[0.167,0.167,0.167],"y":[0.167,0.167,0.167]},"n":["0p833_0p833_0p167_0p167","0p833_0p833_0p167_0p167","0p833_0p833_0p167_0p167"],"t":215,"s":[100,100,100],"e":[0,0,100]},{"i":{"x":[0.833,0.833,0.833],"y":[0.833,0.833,0.833]},"o":{"x":[0.167,0.167,0.167],"y":[0.167,0.167,0.167]},"n":["0p833_0p833_0p167_0p167","0p833_0p833_0p167_0p167","0p833_0p833_0p167_0p167"],"t":255,"s":[0,0,100],"e":[100,100,100]},{"i":{"x":[0.833,0.833,0.833],"y":[0.833,0.833,0.833]},"o":{"x":[0.167,0.167,0.167],"y":[0.167,0.167,0.167]},"n":["0p833_0p833_0p167_0p167","0p833_0p833_0p167_0p167","0p833_0p833_0p167_0p167"],"t":295,"s":[100,100,100],"e":[0,0,100]},{"i":{"x":[0.833,0.833,0.833],"y":[0.833,0.833,0.833]},"o":{"x":[0.167,0.167,0.167],"y":[0.167,0.167,0.167]},"n":["0p833_0p833_0p167_0p167","0p833_0p833_0p167_0p167","0p833_0p833_0p167_0p167"],"t":335,"s":[0,0,100],"e":[100,100,100]},{"i":{"x":[0.833,0.833,0.833],"y":[0.833,0.833,0.833]},"o":{"x":[0.167,0.167,0.167],"y":[0.167,0.167,0.167]},"n":["0p833_0p833_0p167_0p167","0p833_0p833_0p167_0p167","0p833_0p833_0p167_0p167"],"t":375,"s":[100,100,100],"e":[0,0,100]},{"i":{"x":[0.833,0.833,0.833],"y":[0.833,0.833,0.833]},"o":{"x":[0.167,0.167,0.167],"y":[0.167,0.167,0.167]},"n":["0p833_0p833_0p167_0p167","0p833_0p833_0p167_0p167","0p833_0p833_0p167_0p167"],"t":415,"s":[0,0,100],"e":[100,100,100]},{"i":{"x":[0.833,0.833,0.833],"y":[0.833,0.833,0.833]},"o":{"x":[0.167,0.167,0.167],"y":[0.167,0.167,0.167]},"n":["0p833_0p833_0p167_0p167","0p833_0p833_0p167_0p167","0p833_0p833_0p167_0p167"],"t":455,"s":[100,100,100],"e":[0,0,100]},{"i":{"x":[0.833,0.833,0.833],"y":[0.833,0.833,0.833]},"o":{"x":[0.167,0.167,0.167],"y":[0.167,0.167,0.167]},"n":["0p833_0p833_0p167_0p167","0p833_0p833_0p167_0p167","0p833_0p833_0p167_0p167"],"t":495,"s":[0,0,100],"e":[100,100,100]},{"i":{"x":[0.833,0.833,0.833],"y":[0.833,0.833,0.833]},"o":{"x":[0.167,0.167,0.167],"y":[0.167,0.167,0.167]},"n":["0p833_0p833_0p167_0p167","0p833_0p833_0p167_0p167","0p833_0p833_0p167_0p167"],"t":535,"s":[100,100,100],"e":[0,0,100]},{"t":575}],"ix":6,"x":"var $bm_rt;\n$bm_rt = loopOut('cycle', 0);"}},"ao":0,"ip":15,"op":241,"st":15,"bm":0},{"ddd":0,"ind":15,"ty":2,"nm":"点4","refId":"image_10","sr":1,"ks":{"o":{"a":0,"k":100,"ix":11},"r":{"a":0,"k":0,"ix":10},"p":{"a":0,"k":[727,166,0],"ix":2},"a":{"a":0,"k":[4,4,0],"ix":1},"s":{"a":1,"k":[{"i":{"x":[0.833,0.833,0.833],"y":[0.833,0.833,0.833]},"o":{"x":[0.167,0.167,0.167],"y":[0.167,0.167,0.167]},"n":["0p833_0p833_0p167_0p167","0p833_0p833_0p167_0p167","0p833_0p833_0p167_0p167"],"t":20,"s":[0,0,100],"e":[100,100,100]},{"i":{"x":[0.833,0.833,0.833],"y":[0.833,0.833,0.833]},"o":{"x":[0.167,0.167,0.167],"y":[0.167,0.167,0.167]},"n":["0p833_0p833_0p167_0p167","0p833_0p833_0p167_0p167","0p833_0p833_0p167_0p167"],"t":60,"s":[100,100,100],"e":[0,0,100]},{"i":{"x":[0.833,0.833,0.833],"y":[0.833,0.833,0.833]},"o":{"x":[0.167,0.167,0.167],"y":[0.167,0.167,0.167]},"n":["0p833_0p833_0p167_0p167","0p833_0p833_0p167_0p167","0p833_0p833_0p167_0p167"],"t":100,"s":[0,0,100],"e":[100,100,100]},{"i":{"x":[0.833,0.833,0.833],"y":[0.833,0.833,0.833]},"o":{"x":[0.167,0.167,0.167],"y":[0.167,0.167,0.167]},"n":["0p833_0p833_0p167_0p167","0p833_0p833_0p167_0p167","0p833_0p833_0p167_0p167"],"t":140,"s":[100,100,100],"e":[0,0,100]},{"i":{"x":[0.833,0.833,0.833],"y":[0.833,0.833,0.833]},"o":{"x":[0.167,0.167,0.167],"y":[0.167,0.167,0.167]},"n":["0p833_0p833_0p167_0p167","0p833_0p833_0p167_0p167","0p833_0p833_0p167_0p167"],"t":180,"s":[0,0,100],"e":[100,100,100]},{"i":{"x":[0.833,0.833,0.833],"y":[0.833,0.833,0.833]},"o":{"x":[0.167,0.167,0.167],"y":[0.167,0.167,0.167]},"n":["0p833_0p833_0p167_0p167","0p833_0p833_0p167_0p167","0p833_0p833_0p167_0p167"],"t":220,"s":[100,100,100],"e":[0,0,100]},{"i":{"x":[0.833,0.833,0.833],"y":[0.833,0.833,0.833]},"o":{"x":[0.167,0.167,0.167],"y":[0.167,0.167,0.167]},"n":["0p833_0p833_0p167_0p167","0p833_0p833_0p167_0p167","0p833_0p833_0p167_0p167"],"t":260,"s":[0,0,100],"e":[100,100,100]},{"i":{"x":[0.833,0.833,0.833],"y":[0.833,0.833,0.833]},"o":{"x":[0.167,0.167,0.167],"y":[0.167,0.167,0.167]},"n":["0p833_0p833_0p167_0p167","0p833_0p833_0p167_0p167","0p833_0p833_0p167_0p167"],"t":300,"s":[100,100,100],"e":[0,0,100]},{"i":{"x":[0.833,0.833,0.833],"y":[0.833,0.833,0.833]},"o":{"x":[0.167,0.167,0.167],"y":[0.167,0.167,0.167]},"n":["0p833_0p833_0p167_0p167","0p833_0p833_0p167_0p167","0p833_0p833_0p167_0p167"],"t":340,"s":[0,0,100],"e":[100,100,100]},{"i":{"x":[0.833,0.833,0.833],"y":[0.833,0.833,0.833]},"o":{"x":[0.167,0.167,0.167],"y":[0.167,0.167,0.167]},"n":["0p833_0p833_0p167_0p167","0p833_0p833_0p167_0p167","0p833_0p833_0p167_0p167"],"t":380,"s":[100,100,100],"e":[0,0,100]},{"i":{"x":[0.833,0.833,0.833],"y":[0.833,0.833,0.833]},"o":{"x":[0.167,0.167,0.167],"y":[0.167,0.167,0.167]},"n":["0p833_0p833_0p167_0p167","0p833_0p833_0p167_0p167","0p833_0p833_0p167_0p167"],"t":420,"s":[0,0,100],"e":[100,100,100]},{"i":{"x":[0.833,0.833,0.833],"y":[0.833,0.833,0.833]},"o":{"x":[0.167,0.167,0.167],"y":[0.167,0.167,0.167]},"n":["0p833_0p833_0p167_0p167","0p833_0p833_0p167_0p167","0p833_0p833_0p167_0p167"],"t":460,"s":[100,100,100],"e":[0,0,100]},{"i":{"x":[0.833,0.833,0.833],"y":[0.833,0.833,0.833]},"o":{"x":[0.167,0.167,0.167],"y":[0.167,0.167,0.167]},"n":["0p833_0p833_0p167_0p167","0p833_0p833_0p167_0p167","0p833_0p833_0p167_0p167"],"t":500,"s":[0,0,100],"e":[100,100,100]},{"i":{"x":[0.833,0.833,0.833],"y":[0.833,0.833,0.833]},"o":{"x":[0.167,0.167,0.167],"y":[0.167,0.167,0.167]},"n":["0p833_0p833_0p167_0p167","0p833_0p833_0p167_0p167","0p833_0p833_0p167_0p167"],"t":540,"s":[100,100,100],"e":[0,0,100]},{"t":580}],"ix":6,"x":"var $bm_rt;\n$bm_rt = loopOut('cycle', 0);"}},"ao":0,"ip":20,"op":241,"st":20,"bm":0},{"ddd":0,"ind":16,"ty":2,"nm":"星球绿","refId":"image_11","sr":1,"ks":{"o":{"a":0,"k":100,"ix":11},"r":{"a":0,"k":0,"ix":10},"p":{"a":1,"k":[{"i":{"x":0.4,"y":1},"o":{"x":0.001,"y":0},"n":"0p4_1_0p001_0","t":15,"s":[-90,78,0],"e":[140.226,78.57,0],"to":[33.6666679382324,0.08333333581686,0],"ti":[-0.33666667342186,-0.00083333335351,0]},{"i":{"x":0.6,"y":1},"o":{"x":0.4,"y":0},"n":"0p6_1_0p4_0","t":31.354,"s":[140.226,78.57,0],"e":[98.457,78.466,0],"to":[-0.33666667342186,-0.00083333335351,0],"ti":[5.45420742034912,0.01350051350892,0]},{"i":{"x":0.6,"y":1},"o":{"x":0.4,"y":0},"n":"0p6_1_0p4_0","t":53.156,"s":[98.457,78.466,0],"e":[114.37,78.506,0],"to":[5.45420742034912,0.01350051350892,0],"ti":[-0.33666667342186,-0.00083333335351,0]},{"i":{"x":0.6,"y":1},"o":{"x":0.4,"y":0},"n":"0p6_1_0p4_0","t":76.619,"s":[114.37,78.506,0],"e":[112,78.5,0],"to":[-0.33666667342186,-0.00083333335351,0],"ti":[-2.32493853569031,-0.00575479865074,0]},{"t":94}],"ix":2},"a":{"a":0,"k":[75,66.5,0],"ix":1},"s":{"a":0,"k":[100,100,100],"ix":6}},"ao":0,"ip":15,"op":241,"st":15,"bm":0},{"ddd":0,"ind":17,"ty":2,"nm":"星球黄 2","refId":"image_12","sr":1,"ks":{"o":{"a":0,"k":100,"ix":11},"r":{"a":0,"k":0,"ix":10},"p":{"a":1,"k":[{"i":{"x":0.6,"y":1},"o":{"x":0.001,"y":0},"n":"0p6_1_0p001_0","t":15,"s":[1040,185.5,0],"e":[980,185.5,0],"to":[-10,0,0],"ti":[0.69060510396957,0,0]},{"i":{"x":0.4,"y":1},"o":{"x":0.167,"y":0},"n":"0p4_1_0p167_0","t":25.363,"s":[980,185.5,0],"e":[971.86,185.5,0],"to":[-0.00690605118871,0,0],"ti":[0.00690605118871,0,0]},{"i":{"x":0.641,"y":1},"o":{"x":0.4,"y":0},"n":"0p641_1_0p4_0","t":31.146,"s":[971.86,185.5,0],"e":[980,185.5,0],"to":[0.00690605118871,0,0],"ti":[-0.00412550428882,0,0]},{"i":{"x":0.6,"y":1},"o":{"x":0.167,"y":0},"n":"0p6_1_0p167_0","t":48.76,"s":[980,185.5,0],"e":[980.626,185.5,0],"to":[0.0412550419569,0,0],"ti":[-0.369510024786,0,0]},{"i":{"x":0.641,"y":1},"o":{"x":0.4,"y":0},"n":"0p641_1_0p4_0","t":52.674,"s":[980.626,185.5,0],"e":[980,185.5,0],"to":[-0.369510024786,0,0],"ti":[0.0412550419569,0,0]},{"i":{"x":0.6,"y":1},"o":{"x":0.167,"y":0},"n":"0p6_1_0p167_0","t":63.949,"s":[980,185.5,0],"e":[979.316,185.5,0],"to":[-0.00412550428882,0,0],"ti":[0.00690605118871,0,0]},{"i":{"x":0.6,"y":1},"o":{"x":0.4,"y":0},"n":"0p6_1_0p4_0","t":75.84,"s":[979.316,185.5,0],"e":[980,185.5,0],"to":[0.00690605118871,0,0],"ti":[0.00234218640253,0,0]},{"t":93}],"ix":2},"a":{"a":0,"k":[81,80.5,0],"ix":1},"s":{"a":0,"k":[100,100,100],"ix":6}},"ao":0,"ip":15,"op":241,"st":15,"bm":0},{"ddd":0,"ind":18,"ty":2,"nm":"流星1","refId":"image_13","sr":1,"ks":{"o":{"a":0,"k":100,"ix":11},"r":{"a":0,"k":0,"ix":10},"p":{"a":1,"k":[{"i":{"x":0.833,"y":0.833},"o":{"x":0.167,"y":0.167},"n":"0p833_0p833_0p167_0p167","t":30,"s":[-150,145,0],"e":[754,833,0],"to":[150.66667175293,114.666664123535,0],"ti":[-150.66667175293,-114.666664123535,0]},{"t":240}],"ix":2},"a":{"a":0,"k":[64,40,0],"ix":1},"s":{"a":0,"k":[100,100,100],"ix":6}},"ao":0,"ip":30,"op":241,"st":30,"bm":0},{"ddd":0,"ind":19,"ty":2,"nm":"流星2","refId":"image_14","sr":1,"ks":{"o":{"a":0,"k":100,"ix":11},"r":{"a":0,"k":0,"ix":10},"p":{"a":1,"k":[{"i":{"x":0.833,"y":0.833},"o":{"x":0.167,"y":0.167},"n":"0p833_0p833_0p167_0p167","t":5,"s":[-43,-148.5,0],"e":[1027.484,720.861,0],"to":[178.414077758789,144.893447875977,0],"ti":[-178.414077758789,-144.893447875977,0]},{"t":215}],"ix":2},"a":{"a":0,"k":[84.5,50.5,0],"ix":1},"s":{"a":0,"k":[100,100,100],"ix":6}},"ao":0,"ip":5,"op":241,"st":5,"bm":0},{"ddd":0,"ind":20,"ty":2,"nm":"星球","refId":"image_15","sr":1,"ks":{"o":{"a":0,"k":100,"ix":11},"r":{"a":0,"k":0,"ix":10},"p":{"a":1,"k":[{"i":{"x":0.4,"y":1},"o":{"x":0.001,"y":0},"n":"0p4_1_0p001_0","t":5,"s":[476,911.5,0],"e":[476,549.065,0],"to":[0,-53,0],"ti":[0,0.52999997138977,0]},{"i":{"x":0.6,"y":1},"o":{"x":0.4,"y":0},"n":"0p6_1_0p4_0","t":21.561,"s":[476,549.065,0],"e":[476,614.804,0],"to":[0,0.52999997138977,0],"ti":[0,-8.57903289794922,0]},{"i":{"x":0.6,"y":1},"o":{"x":0.4,"y":0},"n":"0p6_1_0p4_0","t":43.641,"s":[476,614.804,0],"e":[476,589.769,0],"to":[0,-8.57903289794922,0],"ti":[0,0.52999997138977,0]},{"i":{"x":0.6,"y":1},"o":{"x":0.4,"y":0},"n":"0p6_1_0p4_0","t":67.4,"s":[476,589.769,0],"e":[476,593.5,0],"to":[0,0.52999997138977,0],"ti":[0,3.65765333175659,0]},{"t":85}],"ix":2},"a":{"a":0,"k":[552,190.5,0],"ix":1},"s":{"a":0,"k":[100,100,100],"ix":6}},"ao":0,"ip":5,"op":241,"st":5,"bm":0},{"ddd":0,"ind":21,"ty":2,"nm":"4","refId":"image_16","sr":1,"ks":{"o":{"a":0,"k":100,"ix":11},"r":{"a":0,"k":0,"ix":10},"p":{"a":1,"k":[{"i":{"x":0.4,"y":1},"o":{"x":0.001,"y":0},"n":"0p4_1_0p001_0","t":10,"s":[113.5,965,0],"e":[113.5,554.696,0],"to":[0,-60,0],"ti":[0,0.60000002384186,0]},{"i":{"x":0.6,"y":1},"o":{"x":0.4,"y":0},"n":"0p6_1_0p4_0","t":26.561,"s":[113.5,554.696,0],"e":[113.5,629.117,0],"to":[0,0.60000002384186,0],"ti":[0,-9.71192646026611,0]},{"i":{"x":0.6,"y":1},"o":{"x":0.4,"y":0},"n":"0p6_1_0p4_0","t":48.641,"s":[113.5,629.117,0],"e":[113.5,600.776,0],"to":[0,-9.71192646026611,0],"ti":[0,0.60000002384186,0]},{"i":{"x":0.6,"y":1},"o":{"x":0.4,"y":0},"n":"0p6_1_0p4_0","t":72.4,"s":[113.5,600.776,0],"e":[113.5,605,0],"to":[0,0.60000002384186,0],"ti":[0,4.14067983627319,0]},{"t":90}],"ix":2},"a":{"a":0,"k":[113.5,115,0],"ix":1},"s":{"a":0,"k":[100,100,100],"ix":6}},"ao":0,"ip":10,"op":241,"st":10,"bm":0},{"ddd":0,"ind":22,"ty":2,"nm":"3","refId":"image_17","sr":1,"ks":{"o":{"a":0,"k":100,"ix":11},"r":{"a":0,"k":0,"ix":10},"p":{"a":1,"k":[{"i":{"x":0.4,"y":1},"o":{"x":0.001,"y":0},"n":"0p4_1_0p001_0","t":10,"s":[831,977.5,0],"e":[831,567.196,0],"to":[0,-60,0],"ti":[0,0.60000002384186,0]},{"i":{"x":0.6,"y":1},"o":{"x":0.4,"y":0},"n":"0p6_1_0p4_0","t":26.561,"s":[831,567.196,0],"e":[831,641.618,0],"to":[0,0.60000002384186,0],"ti":[0,-9.71211338043213,0]},{"i":{"x":0.6,"y":1},"o":{"x":0.4,"y":0},"n":"0p6_1_0p4_0","t":48.641,"s":[831,641.618,0],"e":[831,613.276,0],"to":[0,-9.71211338043213,0],"ti":[0,0.60000002384186,0]},{"i":{"x":0.6,"y":1},"o":{"x":0.4,"y":0},"n":"0p6_1_0p4_0","t":72.4,"s":[831,613.276,0],"e":[831,617.5,0],"to":[0,0.60000002384186,0],"ti":[0,4.14073944091797,0]},{"t":90}],"ix":2},"a":{"a":0,"k":[129,102.5,0],"ix":1},"s":{"a":0,"k":[100,100,100],"ix":6}},"ao":0,"ip":10,"op":241,"st":10,"bm":0},{"ddd":0,"ind":23,"ty":2,"nm":"2","refId":"image_18","sr":1,"ks":{"o":{"a":0,"k":100,"ix":11},"r":{"a":0,"k":0,"ix":10},"p":{"a":1,"k":[{"i":{"x":0.4,"y":1},"o":{"x":0.001,"y":0},"n":"0p4_1_0p001_0","t":15,"s":[214.5,901.5,0],"e":[214.5,491.196,0],"to":[0,-60,0],"ti":[0,0.60000002384186,0]},{"i":{"x":0.6,"y":1},"o":{"x":0.4,"y":0},"n":"0p6_1_0p4_0","t":31.561,"s":[214.5,491.196,0],"e":[214.5,565.618,0],"to":[0,0.60000002384186,0],"ti":[0,-9.71211338043213,0]},{"i":{"x":0.6,"y":1},"o":{"x":0.4,"y":0},"n":"0p6_1_0p4_0","t":53.641,"s":[214.5,565.618,0],"e":[214.5,537.276,0],"to":[0,-9.71211338043213,0],"ti":[0,0.60000002384186,0]},{"i":{"x":0.6,"y":1},"o":{"x":0.4,"y":0},"n":"0p6_1_0p4_0","t":77.4,"s":[214.5,537.276,0],"e":[214.5,541.5,0],"to":[0,0.60000002384186,0],"ti":[0,4.14073944091797,0]},{"t":95}],"ix":2},"a":{"a":0,"k":[214.5,178.5,0],"ix":1},"s":{"a":0,"k":[100,100,100],"ix":6}},"ao":0,"ip":15,"op":241,"st":15,"bm":0},{"ddd":0,"ind":24,"ty":2,"nm":"1","refId":"image_19","sr":1,"ks":{"o":{"a":0,"k":100,"ix":11},"r":{"a":0,"k":0,"ix":10},"p":{"a":1,"k":[{"i":{"x":0.4,"y":1},"o":{"x":0.001,"y":0},"n":"0p4_1_0p001_0","t":15,"s":[728.5,883.5,0],"e":[728.5,473.196,0],"to":[0,-60,0],"ti":[0,0.60000002384186,0]},{"i":{"x":0.6,"y":1},"o":{"x":0.4,"y":0},"n":"0p6_1_0p4_0","t":31.561,"s":[728.5,473.196,0],"e":[728.5,547.617,0],"to":[0,0.60000002384186,0],"ti":[0,-9.71192646026611,0]},{"i":{"x":0.6,"y":1},"o":{"x":0.4,"y":0},"n":"0p6_1_0p4_0","t":53.641,"s":[728.5,547.617,0],"e":[728.5,519.276,0],"to":[0,-9.71192646026611,0],"ti":[0,0.60000002384186,0]},{"i":{"x":0.6,"y":1},"o":{"x":0.4,"y":0},"n":"0p6_1_0p4_0","t":77.4,"s":[728.5,519.276,0],"e":[728.5,523.5,0],"to":[0,0.60000002384186,0],"ti":[0,4.14067983627319,0]},{"t":95}],"ix":2},"a":{"a":0,"k":[231.5,196.5,0],"ix":1},"s":{"a":0,"k":[100,100,100],"ix":6}},"ao":0,"ip":15,"op":241,"st":15,"bm":0}],"markers":[]}