{"v":"5.4.1","fr":25,"ip":0,"op":126,"w":1920,"h":1440,"nm":"赞","ddd":0,"assets":[{"id":"image_0","w":203,"h":72,"u":"images/","p":"img_0.png","e":0},{"id":"image_1","w":268,"h":71,"u":"images/","p":"img_1.png","e":0},{"id":"image_2","w":33,"h":12,"u":"images/","p":"img_2.png","e":0},{"id":"image_3","w":34,"h":25,"u":"images/","p":"img_3.png","e":0},{"id":"image_4","w":97,"h":54,"u":"images/","p":"img_4.png","e":0},{"id":"image_5","w":87,"h":48,"u":"images/","p":"img_5.png","e":0},{"id":"image_6","w":113,"h":65,"u":"images/","p":"img_6.png","e":0},{"id":"image_7","w":56,"h":31,"u":"images/","p":"img_7.png","e":0},{"id":"image_8","w":103,"h":84,"u":"images/","p":"img_8.png","e":0},{"id":"image_9","w":147,"h":82,"u":"images/","p":"img_9.png","e":0},{"id":"image_10","w":110,"h":63,"u":"images/","p":"img_10.png","e":0},{"id":"image_11","w":135,"h":78,"u":"images/","p":"img_11.png","e":0},{"id":"image_12","w":188,"h":95,"u":"images/","p":"img_12.png","e":0},{"id":"image_13","w":78,"h":64,"u":"images/","p":"img_13.png","e":0},{"id":"image_14","w":69,"h":56,"u":"images/","p":"img_14.png","e":0},{"id":"image_15","w":625,"h":270,"u":"images/","p":"img_15.png","e":0},{"id":"image_16","w":211,"h":227,"u":"images/","p":"img_16.png","e":0},{"id":"image_17","w":553,"h":526,"u":"images/","p":"img_17.png","e":0},{"id":"image_18","w":174,"h":139,"u":"images/","p":"img_18.png","e":0},{"id":"image_19","w":31,"h":14,"u":"images/","p":"img_19.png","e":0},{"id":"image_20","w":31,"h":14,"u":"images/","p":"img_20.png","e":0},{"id":"image_21","w":35,"h":14,"u":"images/","p":"img_21.png","e":0},{"id":"image_22","w":33,"h":12,"u":"images/","p":"img_22.png","e":0},{"id":"image_23","w":500,"h":500,"u":"images/","p":"img_23.png","e":0},{"id":"image_24","w":912,"h":858,"u":"images/","p":"img_24.png","e":0}],"layers":[{"ddd":0,"ind":1,"ty":2,"nm":"云彩1 拷贝","refId":"image_0","sr":1,"ks":{"o":{"a":0,"k":100,"ix":11},"r":{"a":0,"k":0,"ix":10},"p":{"a":1,"k":[{"i":{"x":0.833,"y":0.833},"o":{"x":0.167,"y":0.167},"n":"0p833_0p833_0p167_0p167","t":74,"s":[1205.5,765,0],"e":[1179.5,765,0],"to":[-4.33333349227905,0,0],"ti":[0,0,0]},{"i":{"x":0.833,"y":0.833},"o":{"x":0.167,"y":0.167},"n":"0p833_0p833_0p167_0p167","t":143,"s":[1179.5,765,0],"e":[1205.5,765,0],"to":[0,0,0],"ti":[-0.16666667163372,0,0]},{"i":{"x":0.833,"y":0.833},"o":{"x":0.167,"y":0.167},"n":"0p833_0p833_0p167_0p167","t":206,"s":[1205.5,765,0],"e":[1180.5,765,0],"to":[0.16666667163372,0,0],"ti":[0.16666667163372,0,0]},{"i":{"x":0.833,"y":0.833},"o":{"x":0.167,"y":0.167},"n":"0p833_0p833_0p167_0p167","t":281,"s":[1180.5,765,0],"e":[1204.5,765,0],"to":[-0.16666667163372,0,0],"ti":[-4,0,0]},{"t":350}],"ix":2},"a":{"a":0,"k":[101.5,36,0],"ix":1},"s":{"a":0,"k":[100,100,100],"ix":6}},"ao":0,"hasMask":true,"masksProperties":[{"inv":false,"mode":"a","pt":{"a":1,"k":[{"i":{"x":0.667,"y":1},"o":{"x":0.333,"y":0},"n":"0p667_1_0p333_0","t":47,"s":[{"i":[[0,0],[0,0],[0,0],[0,0]],"o":[[0,0],[0,0],[0,0],[0,0]],"v":[[247.5,-13.359],[-59.221,-13.359],[-57.221,-5],[249.5,-5]],"c":true}],"e":[{"i":[[0,0],[0,0],[0,0],[0,0]],"o":[[0,0],[0,0],[0,0],[0,0]],"v":[[247.5,-13.359],[-59.221,-13.359],[-63.221,87],[243.5,87]],"c":true}]},{"t":74}],"ix":1},"o":{"a":0,"k":100,"ix":3},"x":{"a":0,"k":0,"ix":4},"nm":"蒙版 1"},{"inv":true,"mode":"i","pt":{"a":1,"k":[{"i":{"x":0.833,"y":0.833},"o":{"x":0.167,"y":0.167},"n":"0p833_0p833_0p167_0p167","t":74,"s":[{"i":[[0,0],[0,0],[0,0],[0,0]],"o":[[0,0],[0,0],[0,0],[0,0]],"v":[[91.33,-5],[43,-5],[43,11.816],[91.33,11.816]],"c":true}],"e":[{"i":[[0,0],[0,0],[0,0],[0,0]],"o":[[0,0],[0,0],[0,0],[0,0]],"v":[[115.83,-4],[43,-5],[43,11.816],[115.83,12.816]],"c":true}]},{"i":{"x":0.833,"y":0.833},"o":{"x":0.167,"y":0.167},"n":"0p833_0p833_0p167_0p167","t":143,"s":[{"i":[[0,0],[0,0],[0,0],[0,0]],"o":[[0,0],[0,0],[0,0],[0,0]],"v":[[115.83,-4],[43,-5],[43,11.816],[115.83,12.816]],"c":true}],"e":[{"i":[[0,0],[0,0],[0,0],[0,0]],"o":[[0,0],[0,0],[0,0],[0,0]],"v":[[90.83,-5.5],[43,-5],[43,11.816],[90.83,11.316]],"c":true}]},{"i":{"x":0.833,"y":0.833},"o":{"x":0.167,"y":0.167},"n":"0p833_0p833_0p167_0p167","t":206,"s":[{"i":[[0,0],[0,0],[0,0],[0,0]],"o":[[0,0],[0,0],[0,0],[0,0]],"v":[[90.83,-5.5],[43,-5],[43,11.816],[90.83,11.316]],"c":true}],"e":[{"i":[[0,0],[0,0],[0,0],[0,0]],"o":[[0,0],[0,0],[0,0],[0,0]],"v":[[115.33,-5],[43,-5],[43,11.816],[115.33,11.816]],"c":true}]},{"i":{"x":0.833,"y":0.833},"o":{"x":0.167,"y":0.167},"n":"0p833_0p833_0p167_0p167","t":281,"s":[{"i":[[0,0],[0,0],[0,0],[0,0]],"o":[[0,0],[0,0],[0,0],[0,0]],"v":[[115.33,-5],[43,-5],[43,11.816],[115.33,11.816]],"c":true}],"e":[{"i":[[0,0],[0,0],[0,0],[0,0]],"o":[[0,0],[0,0],[0,0],[0,0]],"v":[[90.33,-4],[43,-5],[43,11.816],[90.33,12.816]],"c":true}]},{"t":350}],"ix":1},"o":{"a":0,"k":100,"ix":3},"x":{"a":0,"k":0,"ix":4},"nm":"蒙版 2"}],"ip":0,"op":126,"st":-39,"bm":0},{"ddd":0,"ind":2,"ty":2,"nm":"云彩2 拷贝","refId":"image_1","sr":1,"ks":{"o":{"a":0,"k":100,"ix":11},"r":{"a":0,"k":0,"ix":10},"p":{"a":1,"k":[{"i":{"x":0.833,"y":0.833},"o":{"x":0.167,"y":0.167},"n":"0p833_0p833_0p167_0p167","t":74,"s":[678,876.5,0],"e":[713,876.5,0],"to":[5.83333349227905,0,0],"ti":[0,0,0]},{"i":{"x":0.833,"y":0.833},"o":{"x":0.167,"y":0.167},"n":"0p833_0p833_0p167_0p167","t":143,"s":[713,876.5,0],"e":[678,876.5,0],"to":[0,0,0],"ti":[-0.16666667163372,0,0]},{"i":{"x":0.833,"y":0.833},"o":{"x":0.167,"y":0.167},"n":"0p833_0p833_0p167_0p167","t":206,"s":[678,876.5,0],"e":[714,876.5,0],"to":[0.16666667163372,0,0],"ti":[0.16666667163372,0,0]},{"i":{"x":0.833,"y":0.833},"o":{"x":0.167,"y":0.167},"n":"0p833_0p833_0p167_0p167","t":281,"s":[714,876.5,0],"e":[677,876.5,0],"to":[-0.16666667163372,0,0],"ti":[6.16666650772095,0,0]},{"t":350}],"ix":2},"a":{"a":0,"k":[134,35.5,0],"ix":1},"s":{"a":0,"k":[100,100,100],"ix":6}},"ao":0,"hasMask":true,"masksProperties":[{"inv":false,"mode":"a","pt":{"a":1,"k":[{"i":{"x":0.667,"y":1},"o":{"x":0.333,"y":0},"n":"0p667_1_0p333_0","t":48,"s":[{"i":[[0,0],[0,0],[0,0],[0,0]],"o":[[0,0],[0,0],[0,0],[0,0]],"v":[[306.305,-149],[-113,-149],[-113,-9.535],[306.305,-9.535]],"c":true}],"e":[{"i":[[0,0],[0,0],[0,0],[0,0]],"o":[[0,0],[0,0],[0,0],[0,0]],"v":[[302.305,-36],[-117,-36],[-117,103.465],[302.305,103.465]],"c":true}]},{"t":74}],"ix":1},"o":{"a":0,"k":100,"ix":3},"x":{"a":0,"k":0,"ix":4},"nm":"蒙版 1"}],"ip":0,"op":126,"st":-39,"bm":0},{"ddd":0,"ind":3,"ty":2,"nm":"图层 4","refId":"image_2","sr":1,"ks":{"o":{"a":1,"k":[{"i":{"x":[0.833],"y":[0.833]},"o":{"x":[0.167],"y":[0.167]},"n":["0p833_0p833_0p167_0p167"],"t":89,"s":[0],"e":[100]},{"t":98}],"ix":11},"r":{"a":1,"k":[{"i":{"x":[0.833],"y":[0.833]},"o":{"x":[0.167],"y":[0.167]},"n":["0p833_0p833_0p167_0p167"],"t":89,"s":[0],"e":[45]},{"i":{"x":[0.833],"y":[0.833]},"o":{"x":[0.167],"y":[0.167]},"n":["0p833_0p833_0p167_0p167"],"t":157,"s":[45],"e":[-18]},{"i":{"x":[0.833],"y":[0.833]},"o":{"x":[0.167],"y":[0.167]},"n":["0p833_0p833_0p167_0p167"],"t":220,"s":[-18],"e":[34]},{"i":{"x":[0.833],"y":[0.833]},"o":{"x":[0.167],"y":[0.167]},"n":["0p833_0p833_0p167_0p167"],"t":295,"s":[34],"e":[16]},{"t":364}],"ix":10},"p":{"a":1,"k":[{"i":{"x":0.667,"y":1},"o":{"x":0.333,"y":0},"n":"0p667_1_0p333_0","t":89,"s":[783.5,541,0],"e":[667.5,622,0],"to":[0,0,0],"ti":[99.5,-13.5,0]},{"i":{"x":0.667,"y":1},"o":{"x":0.333,"y":0},"n":"0p667_1_0p333_0","t":157,"s":[667.5,622,0],"e":[796.5,681,0],"to":[69.2465515136719,64.7881546020508,0],"ti":[0.64306718111038,-0.91458439826965,0]},{"i":{"x":0.667,"y":1},"o":{"x":0.333,"y":0},"n":"0p667_1_0p333_0","t":220,"s":[796.5,681,0],"e":[685.5,754.5,0],"to":[-45,64,0],"ti":[39,-11,0]},{"i":{"x":0.667,"y":1},"o":{"x":0.333,"y":0},"n":"0p667_1_0p333_0","t":295,"s":[685.5,754.5,0],"e":[773,801.5,0],"to":[54.5,41.5,0],"ti":[0,0,0]},{"t":364}],"ix":2},"a":{"a":0,"k":[16.5,6,0],"ix":1},"s":{"a":0,"k":[100,100,100],"ix":6}},"ao":0,"ip":17,"op":126,"st":17,"bm":0},{"ddd":0,"ind":4,"ty":2,"nm":"图层 3","refId":"image_3","sr":1,"ks":{"o":{"a":1,"k":[{"i":{"x":[0.833],"y":[0.833]},"o":{"x":[0.167],"y":[0.167]},"n":["0p833_0p833_0p167_0p167"],"t":89,"s":[0],"e":[100]},{"t":98}],"ix":11},"r":{"a":1,"k":[{"i":{"x":[0.833],"y":[0.833]},"o":{"x":[0.167],"y":[0.167]},"n":["0p833_0p833_0p167_0p167"],"t":89,"s":[80],"e":[20]},{"i":{"x":[0.833],"y":[0.833]},"o":{"x":[0.167],"y":[0.167]},"n":["0p833_0p833_0p167_0p167"],"t":157,"s":[20],"e":[66]},{"i":{"x":[0.833],"y":[0.833]},"o":{"x":[0.167],"y":[0.167]},"n":["0p833_0p833_0p167_0p167"],"t":220,"s":[66],"e":[26]},{"i":{"x":[0.833],"y":[0.833]},"o":{"x":[0.167],"y":[0.167]},"n":["0p833_0p833_0p167_0p167"],"t":295,"s":[26],"e":[40]},{"t":364}],"ix":10},"p":{"a":1,"k":[{"i":{"x":0.667,"y":1},"o":{"x":0.333,"y":0},"n":"0p667_1_0p333_0","t":89,"s":[1147,568.5,0],"e":[1264,667.5,0],"to":[59.5,85,0],"ti":[1.04422187805176,-1.18726599216461,0]},{"i":{"x":0.667,"y":1},"o":{"x":0.333,"y":0},"n":"0p667_1_0p333_0","t":157,"s":[1264,667.5,0],"e":[1148,727.5,0],"to":[-45,48.5,0],"ti":[0,0,0]},{"i":{"x":0.667,"y":1},"o":{"x":0.333,"y":0},"n":"0p667_1_0p333_0","t":220,"s":[1148,727.5,0],"e":[1265,814.5,0],"to":[0,0,0],"ti":[-103.5,-29.5,0]},{"i":{"x":0.667,"y":1},"o":{"x":0.333,"y":0},"n":"0p667_1_0p333_0","t":295,"s":[1265,814.5,0],"e":[1174,876.5,0],"to":[-24.6130294799805,61.7286529541016,0],"ti":[0,0,0]},{"t":364}],"ix":2},"a":{"a":0,"k":[17,12.5,0],"ix":1},"s":{"a":0,"k":[100,100,100],"ix":6}},"ao":0,"ip":17,"op":126,"st":17,"bm":0},{"ddd":0,"ind":5,"ty":2,"nm":"叶子","refId":"image_4","sr":1,"ks":{"o":{"a":0,"k":100,"ix":11},"r":{"a":0,"k":0,"ix":10},"p":{"a":0,"k":[960,910,0],"ix":2},"a":{"a":0,"k":[49,50,0],"ix":1},"s":{"a":1,"k":[{"i":{"x":[0.4,0.4,0.4],"y":[1,1,1]},"o":{"x":[0.7,0.7,0.7],"y":[0,0,0]},"n":["0p4_1_0p7_0","0p4_1_0p7_0","0p4_1_0p7_0"],"t":22,"s":[0,0,100],"e":[113.1,113.1,100]},{"i":{"x":[0.6,0.6,0.6],"y":[1,1,1]},"o":{"x":[0.4,0.4,0.4],"y":[0,0,0]},"n":["0p6_1_0p4_0","0p6_1_0p4_0","0p6_1_0p4_0"],"t":26.968,"s":[113.1,113.1,100],"e":[98.642,98.642,100]},{"i":{"x":[0.6,0.6,0.6],"y":[1,1,1]},"o":{"x":[0.4,0.4,0.4],"y":[0,0,0]},"n":["0p6_1_0p4_0","0p6_1_0p4_0","0p6_1_0p4_0"],"t":33.592,"s":[98.642,98.642,100],"e":[101.1,101.1,100]},{"i":{"x":[0.6,0.6,0.6],"y":[1,1,1]},"o":{"x":[0.4,0.4,0.4],"y":[0,0,0]},"n":["0p6_1_0p4_0","0p6_1_0p4_0","0p6_1_0p4_0"],"t":40.72,"s":[101.1,101.1,100],"e":[100,100,100]},{"t":46}],"ix":6}},"ao":0,"ip":0,"op":126,"st":-25,"bm":0},{"ddd":0,"ind":6,"ty":2,"nm":"叶子","refId":"image_5","sr":1,"ks":{"o":{"a":0,"k":100,"ix":11},"r":{"a":0,"k":0,"ix":10},"p":{"a":0,"k":[1015.5,893.5,0],"ix":2},"a":{"a":0,"k":[40.5,49.5,0],"ix":1},"s":{"a":1,"k":[{"i":{"x":[0.4,0.4,0.4],"y":[1,1,1]},"o":{"x":[0.7,0.7,0.7],"y":[0,0,0]},"n":["0p4_1_0p7_0","0p4_1_0p7_0","0p4_1_0p7_0"],"t":22,"s":[0,0,100],"e":[113.1,113.1,100]},{"i":{"x":[0.6,0.6,0.6],"y":[1,1,1]},"o":{"x":[0.4,0.4,0.4],"y":[0,0,0]},"n":["0p6_1_0p4_0","0p6_1_0p4_0","0p6_1_0p4_0"],"t":26.968,"s":[113.1,113.1,100],"e":[98.642,98.642,100]},{"i":{"x":[0.6,0.6,0.6],"y":[1,1,1]},"o":{"x":[0.4,0.4,0.4],"y":[0,0,0]},"n":["0p6_1_0p4_0","0p6_1_0p4_0","0p6_1_0p4_0"],"t":33.592,"s":[98.642,98.642,100],"e":[101.1,101.1,100]},{"i":{"x":[0.6,0.6,0.6],"y":[1,1,1]},"o":{"x":[0.4,0.4,0.4],"y":[0,0,0]},"n":["0p6_1_0p4_0","0p6_1_0p4_0","0p6_1_0p4_0"],"t":40.72,"s":[101.1,101.1,100],"e":[100,100,100]},{"t":46}],"ix":6}},"ao":0,"ip":0,"op":126,"st":-25,"bm":0},{"ddd":0,"ind":7,"ty":2,"nm":"叶子","refId":"image_6","sr":1,"ks":{"o":{"a":0,"k":100,"ix":11},"r":{"a":0,"k":0,"ix":10},"p":{"a":0,"k":[955,912.5,0],"ix":2},"a":{"a":0,"k":[64,63.5,0],"ix":1},"s":{"a":1,"k":[{"i":{"x":[0.4,0.4,0.4],"y":[1,1,1]},"o":{"x":[0.7,0.7,0.7],"y":[0,0,0]},"n":["0p4_1_0p7_0","0p4_1_0p7_0","0p4_1_0p7_0"],"t":22,"s":[0,0,100],"e":[113.1,113.1,100]},{"i":{"x":[0.6,0.6,0.6],"y":[1,1,1]},"o":{"x":[0.4,0.4,0.4],"y":[0,0,0]},"n":["0p6_1_0p4_0","0p6_1_0p4_0","0p6_1_0p4_0"],"t":26.968,"s":[113.1,113.1,100],"e":[98.642,98.642,100]},{"i":{"x":[0.6,0.6,0.6],"y":[1,1,1]},"o":{"x":[0.4,0.4,0.4],"y":[0,0,0]},"n":["0p6_1_0p4_0","0p6_1_0p4_0","0p6_1_0p4_0"],"t":33.592,"s":[98.642,98.642,100],"e":[101.1,101.1,100]},{"i":{"x":[0.6,0.6,0.6],"y":[1,1,1]},"o":{"x":[0.4,0.4,0.4],"y":[0,0,0]},"n":["0p6_1_0p4_0","0p6_1_0p4_0","0p6_1_0p4_0"],"t":40.72,"s":[101.1,101.1,100],"e":[100,100,100]},{"t":46}],"ix":6}},"ao":0,"ip":0,"op":126,"st":-25,"bm":0},{"ddd":0,"ind":8,"ty":2,"nm":"叶子","refId":"image_7","sr":1,"ks":{"o":{"a":0,"k":100,"ix":11},"r":{"a":0,"k":0,"ix":10},"p":{"a":0,"k":[797.5,898.5,0],"ix":2},"a":{"a":0,"k":[28.5,30.5,0],"ix":1},"s":{"a":1,"k":[{"i":{"x":[0.4,0.4,0.4],"y":[1,1,1]},"o":{"x":[0.7,0.7,0.7],"y":[0,0,0]},"n":["0p4_1_0p7_0","0p4_1_0p7_0","0p4_1_0p7_0"],"t":17,"s":[0,0,100],"e":[113.1,113.1,100]},{"i":{"x":[0.6,0.6,0.6],"y":[1,1,1]},"o":{"x":[0.4,0.4,0.4],"y":[0,0,0]},"n":["0p6_1_0p4_0","0p6_1_0p4_0","0p6_1_0p4_0"],"t":21.554,"s":[113.1,113.1,100],"e":[98.643,98.643,100]},{"i":{"x":[0.6,0.6,0.6],"y":[1,1,1]},"o":{"x":[0.4,0.4,0.4],"y":[0,0,0]},"n":["0p6_1_0p4_0","0p6_1_0p4_0","0p6_1_0p4_0"],"t":27.626,"s":[98.643,98.643,100],"e":[101.1,101.1,100]},{"i":{"x":[0.6,0.6,0.6],"y":[1,1,1]},"o":{"x":[0.4,0.4,0.4],"y":[0,0,0]},"n":["0p6_1_0p4_0","0p6_1_0p4_0","0p6_1_0p4_0"],"t":34.16,"s":[101.1,101.1,100],"e":[100,100,100]},{"t":39}],"ix":6}},"ao":0,"ip":0,"op":126,"st":-25,"bm":0},{"ddd":0,"ind":9,"ty":2,"nm":"叶子","refId":"image_8","sr":1,"ks":{"o":{"a":0,"k":100,"ix":11},"r":{"a":0,"k":0,"ix":10},"p":{"a":0,"k":[803,899,0],"ix":2},"a":{"a":0,"k":[39,65,0],"ix":1},"s":{"a":1,"k":[{"i":{"x":[0.4,0.4,0.4],"y":[1,1,1]},"o":{"x":[0.7,0.7,0.7],"y":[0,0,0]},"n":["0p4_1_0p7_0","0p4_1_0p7_0","0p4_1_0p7_0"],"t":17,"s":[0,0,100],"e":[113.1,113.1,100]},{"i":{"x":[0.6,0.6,0.6],"y":[1,1,1]},"o":{"x":[0.4,0.4,0.4],"y":[0,0,0]},"n":["0p6_1_0p4_0","0p6_1_0p4_0","0p6_1_0p4_0"],"t":21.554,"s":[113.1,113.1,100],"e":[98.643,98.643,100]},{"i":{"x":[0.6,0.6,0.6],"y":[1,1,1]},"o":{"x":[0.4,0.4,0.4],"y":[0,0,0]},"n":["0p6_1_0p4_0","0p6_1_0p4_0","0p6_1_0p4_0"],"t":27.626,"s":[98.643,98.643,100],"e":[101.1,101.1,100]},{"i":{"x":[0.6,0.6,0.6],"y":[1,1,1]},"o":{"x":[0.4,0.4,0.4],"y":[0,0,0]},"n":["0p6_1_0p4_0","0p6_1_0p4_0","0p6_1_0p4_0"],"t":34.16,"s":[101.1,101.1,100],"e":[100,100,100]},{"t":39}],"ix":6}},"ao":0,"ip":0,"op":126,"st":-25,"bm":0},{"ddd":0,"ind":10,"ty":2,"nm":"叶子","refId":"image_9","sr":1,"ks":{"o":{"a":0,"k":100,"ix":11},"r":{"a":0,"k":0,"ix":10},"p":{"a":0,"k":[805,892.5,0],"ix":2},"a":{"a":0,"k":[76,75.5,0],"ix":1},"s":{"a":1,"k":[{"i":{"x":[0.4,0.4,0.4],"y":[1,1,1]},"o":{"x":[0.7,0.7,0.7],"y":[0,0,0]},"n":["0p4_1_0p7_0","0p4_1_0p7_0","0p4_1_0p7_0"],"t":17,"s":[0,0,100],"e":[113.1,113.1,100]},{"i":{"x":[0.6,0.6,0.6],"y":[1,1,1]},"o":{"x":[0.4,0.4,0.4],"y":[0,0,0]},"n":["0p6_1_0p4_0","0p6_1_0p4_0","0p6_1_0p4_0"],"t":21.554,"s":[113.1,113.1,100],"e":[98.643,98.643,100]},{"i":{"x":[0.6,0.6,0.6],"y":[1,1,1]},"o":{"x":[0.4,0.4,0.4],"y":[0,0,0]},"n":["0p6_1_0p4_0","0p6_1_0p4_0","0p6_1_0p4_0"],"t":27.626,"s":[98.643,98.643,100],"e":[101.1,101.1,100]},{"i":{"x":[0.6,0.6,0.6],"y":[1,1,1]},"o":{"x":[0.4,0.4,0.4],"y":[0,0,0]},"n":["0p6_1_0p4_0","0p6_1_0p4_0","0p6_1_0p4_0"],"t":34.16,"s":[101.1,101.1,100],"e":[100,100,100]},{"t":39}],"ix":6}},"ao":0,"ip":0,"op":126,"st":-25,"bm":0},{"ddd":0,"ind":11,"ty":2,"nm":"叶子","refId":"image_10","sr":1,"ks":{"o":{"a":0,"k":100,"ix":11},"r":{"a":0,"k":0,"ix":10},"p":{"a":0,"k":[1108,874,0],"ix":2},"a":{"a":0,"k":[63,59,0],"ix":1},"s":{"a":1,"k":[{"i":{"x":[0.4,0.4,0.4],"y":[1,1,1]},"o":{"x":[0.7,0.7,0.7],"y":[0,0,0]},"n":["0p4_1_0p7_0","0p4_1_0p7_0","0p4_1_0p7_0"],"t":24,"s":[0,0,100],"e":[113.1,113.1,100]},{"i":{"x":[0.6,0.6,0.6],"y":[1,1,1]},"o":{"x":[0.4,0.4,0.4],"y":[0,0,0]},"n":["0p6_1_0p4_0","0p6_1_0p4_0","0p6_1_0p4_0"],"t":28.968,"s":[113.1,113.1,100],"e":[98.642,98.642,100]},{"i":{"x":[0.6,0.6,0.6],"y":[1,1,1]},"o":{"x":[0.4,0.4,0.4],"y":[0,0,0]},"n":["0p6_1_0p4_0","0p6_1_0p4_0","0p6_1_0p4_0"],"t":35.592,"s":[98.642,98.642,100],"e":[101.1,101.1,100]},{"i":{"x":[0.6,0.6,0.6],"y":[1,1,1]},"o":{"x":[0.4,0.4,0.4],"y":[0,0,0]},"n":["0p6_1_0p4_0","0p6_1_0p4_0","0p6_1_0p4_0"],"t":42.72,"s":[101.1,101.1,100],"e":[100,100,100]},{"t":48}],"ix":6}},"ao":0,"ip":0,"op":126,"st":-25,"bm":0},{"ddd":0,"ind":12,"ty":2,"nm":"叶子","refId":"image_11","sr":1,"ks":{"o":{"a":0,"k":100,"ix":11},"r":{"a":0,"k":0,"ix":10},"p":{"a":0,"k":[1165.5,904,0],"ix":2},"a":{"a":0,"k":[65.5,77,0],"ix":1},"s":{"a":1,"k":[{"i":{"x":[0.4,0.4,0.4],"y":[1,1,1]},"o":{"x":[0.7,0.7,0.7],"y":[0,0,0]},"n":["0p4_1_0p7_0","0p4_1_0p7_0","0p4_1_0p7_0"],"t":25,"s":[0,0,100],"e":[113.1,113.1,100]},{"i":{"x":[0.6,0.6,0.6],"y":[1,1,1]},"o":{"x":[0.4,0.4,0.4],"y":[0,0,0]},"n":["0p6_1_0p4_0","0p6_1_0p4_0","0p6_1_0p4_0"],"t":29.968,"s":[113.1,113.1,100],"e":[98.642,98.642,100]},{"i":{"x":[0.6,0.6,0.6],"y":[1,1,1]},"o":{"x":[0.4,0.4,0.4],"y":[0,0,0]},"n":["0p6_1_0p4_0","0p6_1_0p4_0","0p6_1_0p4_0"],"t":36.592,"s":[98.642,98.642,100],"e":[101.1,101.1,100]},{"i":{"x":[0.6,0.6,0.6],"y":[1,1,1]},"o":{"x":[0.4,0.4,0.4],"y":[0,0,0]},"n":["0p6_1_0p4_0","0p6_1_0p4_0","0p6_1_0p4_0"],"t":43.72,"s":[101.1,101.1,100],"e":[100,100,100]},{"t":49}],"ix":6}},"ao":0,"ip":0,"op":126,"st":-25,"bm":0},{"ddd":0,"ind":13,"ty":2,"nm":"叶子","refId":"image_12","sr":1,"ks":{"o":{"a":0,"k":100,"ix":11},"r":{"a":0,"k":0,"ix":10},"p":{"a":0,"k":[1174,862,0],"ix":2},"a":{"a":0,"k":[94,89,0],"ix":1},"s":{"a":1,"k":[{"i":{"x":[0.4,0.4,0.4],"y":[1,1,1]},"o":{"x":[0.7,0.7,0.7],"y":[0,0,0]},"n":["0p4_1_0p7_0","0p4_1_0p7_0","0p4_1_0p7_0"],"t":29,"s":[0,0,100],"e":[113.1,113.1,100]},{"i":{"x":[0.6,0.6,0.6],"y":[1,1,1]},"o":{"x":[0.4,0.4,0.4],"y":[0,0,0]},"n":["0p6_1_0p4_0","0p6_1_0p4_0","0p6_1_0p4_0"],"t":33.554,"s":[113.1,113.1,100],"e":[98.643,98.643,100]},{"i":{"x":[0.6,0.6,0.6],"y":[1,1,1]},"o":{"x":[0.4,0.4,0.4],"y":[0,0,0]},"n":["0p6_1_0p4_0","0p6_1_0p4_0","0p6_1_0p4_0"],"t":39.626,"s":[98.643,98.643,100],"e":[101.1,101.1,100]},{"i":{"x":[0.6,0.6,0.6],"y":[1,1,1]},"o":{"x":[0.4,0.4,0.4],"y":[0,0,0]},"n":["0p6_1_0p4_0","0p6_1_0p4_0","0p6_1_0p4_0"],"t":46.16,"s":[101.1,101.1,100],"e":[100,100,100]},{"t":51}],"ix":6}},"ao":0,"ip":0,"op":126,"st":-25,"bm":0},{"ddd":0,"ind":14,"ty":2,"nm":"叶子","refId":"image_13","sr":1,"ks":{"o":{"a":0,"k":100,"ix":11},"r":{"a":0,"k":0,"ix":10},"p":{"a":0,"k":[1257.5,982,0],"ix":2},"a":{"a":0,"k":[24.5,47,0],"ix":1},"s":{"a":1,"k":[{"i":{"x":[0.4,0.4,0.4],"y":[1,1,1]},"o":{"x":[0.7,0.7,0.7],"y":[0,0,0]},"n":["0p4_1_0p7_0","0p4_1_0p7_0","0p4_1_0p7_0"],"t":28,"s":[0,0,100],"e":[113.1,113.1,100]},{"i":{"x":[0.6,0.6,0.6],"y":[1,1,1]},"o":{"x":[0.4,0.4,0.4],"y":[0,0,0]},"n":["0p6_1_0p4_0","0p6_1_0p4_0","0p6_1_0p4_0"],"t":32.968,"s":[113.1,113.1,100],"e":[98.642,98.642,100]},{"i":{"x":[0.6,0.6,0.6],"y":[1,1,1]},"o":{"x":[0.4,0.4,0.4],"y":[0,0,0]},"n":["0p6_1_0p4_0","0p6_1_0p4_0","0p6_1_0p4_0"],"t":39.592,"s":[98.642,98.642,100],"e":[101.1,101.1,100]},{"i":{"x":[0.6,0.6,0.6],"y":[1,1,1]},"o":{"x":[0.4,0.4,0.4],"y":[0,0,0]},"n":["0p6_1_0p4_0","0p6_1_0p4_0","0p6_1_0p4_0"],"t":46.72,"s":[101.1,101.1,100],"e":[100,100,100]},{"t":52}],"ix":6}},"ao":0,"ip":0,"op":126,"st":-25,"bm":0},{"ddd":0,"ind":15,"ty":2,"nm":"叶子","refId":"image_14","sr":1,"ks":{"o":{"a":0,"k":100,"ix":11},"r":{"a":0,"k":0,"ix":10},"p":{"a":0,"k":[1233,953.5,0],"ix":2},"a":{"a":0,"k":[24,40.5,0],"ix":1},"s":{"a":1,"k":[{"i":{"x":[0.4,0.4,0.4],"y":[1,1,1]},"o":{"x":[0.7,0.7,0.7],"y":[0,0,0]},"n":["0p4_1_0p7_0","0p4_1_0p7_0","0p4_1_0p7_0"],"t":27,"s":[0,0,100],"e":[113.1,113.1,100]},{"i":{"x":[0.6,0.6,0.6],"y":[1,1,1]},"o":{"x":[0.4,0.4,0.4],"y":[0,0,0]},"n":["0p6_1_0p4_0","0p6_1_0p4_0","0p6_1_0p4_0"],"t":31.761,"s":[113.1,113.1,100],"e":[98.642,98.642,100]},{"i":{"x":[0.6,0.6,0.6],"y":[1,1,1]},"o":{"x":[0.4,0.4,0.4],"y":[0,0,0]},"n":["0p6_1_0p4_0","0p6_1_0p4_0","0p6_1_0p4_0"],"t":38.109,"s":[98.642,98.642,100],"e":[101.1,101.1,100]},{"i":{"x":[0.6,0.6,0.6],"y":[1,1,1]},"o":{"x":[0.4,0.4,0.4],"y":[0,0,0]},"n":["0p6_1_0p4_0","0p6_1_0p4_0","0p6_1_0p4_0"],"t":44.94,"s":[101.1,101.1,100],"e":[100,100,100]},{"t":50}],"ix":6}},"ao":0,"ip":0,"op":126,"st":-25,"bm":0},{"ddd":0,"ind":16,"ty":2,"nm":"树干","refId":"image_15","sr":1,"ks":{"o":{"a":0,"k":100,"ix":11},"r":{"a":0,"k":0,"ix":10},"p":{"a":0,"k":[971.5,894,0],"ix":2},"a":{"a":0,"k":[312.5,135,0],"ix":1},"s":{"a":0,"k":[100,100,100],"ix":6}},"ao":0,"hasMask":true,"masksProperties":[{"inv":false,"mode":"a","pt":{"a":1,"k":[{"i":{"x":0.58,"y":1},"o":{"x":0.827,"y":0},"n":"0p58_1_0p827_0","t":0,"s":[{"i":[[0,0],[0,0],[0,0],[0,0]],"o":[[0,0],[0,0],[0,0],[0,0]],"v":[[60.214,-114.897],[7.593,-148.598],[-124.69,211.877],[-52.069,172.578]],"c":true}],"e":[{"i":[[0,0],[0,0],[0,0],[0,0]],"o":[[0,0],[0,0],[0,0],[0,0]],"v":[[642.054,44.963],[7.593,-148.598],[-124.69,211.877],[653.971,418.058]],"c":true}]},{"t":34}],"ix":1},"o":{"a":0,"k":100,"ix":3},"x":{"a":0,"k":0,"ix":4},"nm":"蒙版 1"}],"ip":0,"op":126,"st":-25,"bm":0},{"ddd":0,"ind":17,"ty":2,"nm":"赞","refId":"image_16","sr":1,"ks":{"o":{"a":0,"k":100,"ix":11},"r":{"a":0,"k":0,"ix":10},"p":{"a":0,"k":[956.5,689.5,0],"ix":2},"a":{"a":0,"k":[105.5,113.5,0],"ix":1},"s":{"a":1,"k":[{"i":{"x":[0.4,0.4,0.4],"y":[1,1,1]},"o":{"x":[0.7,0.7,0.7],"y":[0,0,0]},"n":["0p4_1_0p7_0","0p4_1_0p7_0","0p4_1_0p7_0"],"t":26,"s":[0,0,100],"e":[113.1,113.1,100]},{"i":{"x":[0.6,0.6,0.6],"y":[1,1,1]},"o":{"x":[0.4,0.4,0.4],"y":[0,0,0]},"n":["0p6_1_0p4_0","0p6_1_0p4_0","0p6_1_0p4_0"],"t":31.796,"s":[113.1,113.1,100],"e":[98.959,98.959,100]},{"i":{"x":[0.6,0.6,0.6],"y":[1,1,1]},"o":{"x":[0.4,0.4,0.4],"y":[0,0,0]},"n":["0p6_1_0p4_0","0p6_1_0p4_0","0p6_1_0p4_0"],"t":39.524,"s":[98.959,98.959,100],"e":[101.1,101.1,100]},{"i":{"x":[0.6,0.6,0.6],"y":[1,1,1]},"o":{"x":[0.4,0.4,0.4],"y":[0,0,0]},"n":["0p6_1_0p4_0","0p6_1_0p4_0","0p6_1_0p4_0"],"t":47.84,"s":[101.1,101.1,100],"e":[100,100,100]},{"t":54}],"ix":6}},"ao":0,"ip":0,"op":126,"st":-26,"bm":0},{"ddd":0,"ind":18,"ty":2,"nm":"椭圆 668","refId":"image_17","sr":1,"ks":{"o":{"a":0,"k":100,"ix":11},"r":{"a":0,"k":0,"ix":10},"p":{"a":0,"k":[951.5,700,0],"ix":2},"a":{"a":0,"k":[276.5,263,0],"ix":1},"s":{"a":1,"k":[{"i":{"x":[0.4,0.4,0.4],"y":[1,1,1]},"o":{"x":[0.7,0.7,0.7],"y":[0,0,0]},"n":["0p4_1_0p7_0","0p4_1_0p7_0","0p4_1_0p7_0"],"t":26,"s":[0,0,100],"e":[113.1,113.1,100]},{"i":{"x":[0.6,0.6,0.6],"y":[1,1,1]},"o":{"x":[0.4,0.4,0.4],"y":[0,0,0]},"n":["0p6_1_0p4_0","0p6_1_0p4_0","0p6_1_0p4_0"],"t":31.796,"s":[113.1,113.1,100],"e":[98.642,98.642,100]},{"i":{"x":[0.6,0.6,0.6],"y":[1,1,1]},"o":{"x":[0.4,0.4,0.4],"y":[0,0,0]},"n":["0p6_1_0p4_0","0p6_1_0p4_0","0p6_1_0p4_0"],"t":39.524,"s":[98.642,98.642,100],"e":[101.1,101.1,100]},{"i":{"x":[0.6,0.6,0.6],"y":[1,1,1]},"o":{"x":[0.4,0.4,0.4],"y":[0,0,0]},"n":["0p6_1_0p4_0","0p6_1_0p4_0","0p6_1_0p4_0"],"t":47.84,"s":[101.1,101.1,100],"e":[100,100,100]},{"t":54}],"ix":6}},"ao":0,"ip":0,"op":126,"st":-25,"bm":0},{"ddd":0,"ind":19,"ty":2,"nm":"叶子3","refId":"image_18","sr":1,"ks":{"o":{"a":0,"k":100,"ix":11},"r":{"a":0,"k":0,"ix":10},"p":{"a":0,"k":[723,796,0],"ix":2},"a":{"a":0,"k":[110,124,0],"ix":1},"s":{"a":1,"k":[{"i":{"x":[0.2,0.2,0.2],"y":[1,1,1]},"o":{"x":[0.7,0.7,0.7],"y":[0,0,0]},"n":["0p2_1_0p7_0","0p2_1_0p7_0","0p2_1_0p7_0"],"t":29,"s":[0,0,100],"e":[108.8,108.8,100]},{"i":{"x":[0.5,0.5,0.5],"y":[1,1,1]},"o":{"x":[0.2,0.2,0.2],"y":[0,0,0]},"n":["0p5_1_0p2_0","0p5_1_0p2_0","0p5_1_0p2_0"],"t":35.426,"s":[108.8,108.8,100],"e":[99.4,99.4,100]},{"i":{"x":[0.65,0.65,0.65],"y":[1,1,1]},"o":{"x":[0.35,0.35,0.35],"y":[0,0,0]},"n":["0p65_1_0p35_0","0p65_1_0p35_0","0p65_1_0p35_0"],"t":43.217,"s":[99.4,99.4,100],"e":[100,100,100]},{"t":50}],"ix":6}},"ao":0,"ip":0,"op":126,"st":-25,"bm":0},{"ddd":0,"ind":22,"ty":2,"nm":"叶子","refId":"image_19","sr":1,"ks":{"o":{"a":1,"k":[{"i":{"x":[0.833],"y":[0.833]},"o":{"x":[0.167],"y":[0.167]},"n":["0p833_0p833_0p167_0p167"],"t":176,"s":[100],"e":[0]},{"t":186}],"ix":11},"r":{"a":1,"k":[{"i":{"x":[0.833],"y":[0.833]},"o":{"x":[0.167],"y":[0.167]},"n":["0p833_0p833_0p167_0p167"],"t":50,"s":[0],"e":[33]},{"i":{"x":[0.833],"y":[0.833]},"o":{"x":[0.167],"y":[0.167]},"n":["0p833_0p833_0p167_0p167"],"t":117,"s":[33],"e":[-3]},{"t":186}],"ix":10},"p":{"a":1,"k":[{"i":{"x":0,"y":1},"o":{"x":0.168,"y":0},"n":"0_1_0p168_0","t":31,"s":[946.5,701,0],"e":[570.5,836,0],"to":[-62.6666679382324,22.5,0],"ti":[0,0,0]},{"i":{"x":0.667,"y":1},"o":{"x":0.286,"y":0},"n":"0p667_1_0p286_0","t":50,"s":[570.5,836,0],"e":[676.5,942,0],"to":[0,0,0],"ti":[-99.5,-26,0]},{"i":{"x":0.667,"y":1},"o":{"x":0.333,"y":0},"n":"0p667_1_0p333_0","t":117,"s":[676.5,942,0],"e":[573.5,1024,0],"to":[-37.5,60,0],"ti":[17.1666660308838,-13.6666669845581,0]},{"t":186}],"ix":2},"a":{"a":0,"k":[15.5,7,0],"ix":1},"s":{"a":0,"k":[100,100,100],"ix":6}},"ao":0,"ip":31,"op":126,"st":-39,"bm":0},{"ddd":0,"ind":23,"ty":2,"nm":"叶子2","refId":"image_20","sr":1,"ks":{"o":{"a":1,"k":[{"i":{"x":[0.833],"y":[0.833]},"o":{"x":[0.167],"y":[0.167]},"n":["0p833_0p833_0p167_0p167"],"t":176,"s":[100],"e":[0]},{"t":186}],"ix":11},"r":{"a":1,"k":[{"i":{"x":[0.833],"y":[0.833]},"o":{"x":[0.167],"y":[0.167]},"n":["0p833_0p833_0p167_0p167"],"t":50,"s":[-34],"e":[50]},{"i":{"x":[0.833],"y":[0.833]},"o":{"x":[0.167],"y":[0.167]},"n":["0p833_0p833_0p167_0p167"],"t":117,"s":[50],"e":[-5]},{"t":186}],"ix":10},"p":{"a":1,"k":[{"i":{"x":0,"y":1},"o":{"x":0.188,"y":0},"n":"0_1_0p188_0","t":31,"s":[951.5,696,0],"e":[1084.5,435,0],"to":[0,0,0],"ti":[0,0,0]},{"i":{"x":0.667,"y":1},"o":{"x":0.333,"y":0},"n":"0p667_1_0p333_0","t":50,"s":[1084.5,435,0],"e":[1061,530.5,0],"to":[0,0,0],"ti":[54.25,-31.75,0]},{"i":{"x":0.667,"y":1},"o":{"x":0.333,"y":0},"n":"0p667_1_0p333_0","t":117,"s":[1061,530.5,0],"e":[1145,592.5,0],"to":[25.767147064209,52.5376663208008,0],"ti":[0,0,0]},{"t":186}],"ix":2},"a":{"a":0,"k":[15.5,7,0],"ix":1},"s":{"a":0,"k":[100,100,100],"ix":6}},"ao":0,"ip":31,"op":126,"st":-39,"bm":0},{"ddd":0,"ind":24,"ty":2,"nm":"叶子3","refId":"image_21","sr":1,"ks":{"o":{"a":1,"k":[{"i":{"x":[0.833],"y":[0.833]},"o":{"x":[0.167],"y":[0.167]},"n":["0p833_0p833_0p167_0p167"],"t":239,"s":[100],"e":[0]},{"t":249}],"ix":11},"r":{"a":1,"k":[{"i":{"x":[0.833],"y":[0.833]},"o":{"x":[0.167],"y":[0.167]},"n":["0p833_0p833_0p167_0p167"],"t":50,"s":[0],"e":[2]},{"i":{"x":[0.833],"y":[0.833]},"o":{"x":[0.167],"y":[0.167]},"n":["0p833_0p833_0p167_0p167"],"t":117,"s":[2],"e":[27]},{"i":{"x":[0.833],"y":[0.833]},"o":{"x":[0.167],"y":[0.167]},"n":["0p833_0p833_0p167_0p167"],"t":186,"s":[27],"e":[11]},{"t":249}],"ix":10},"p":{"a":1,"k":[{"i":{"x":0,"y":1},"o":{"x":0.119,"y":0},"n":"0_1_0p119_0","t":31,"s":[969.5,722,0],"e":[1259.5,683,0],"to":[48.3333320617676,-6.5,0],"ti":[0,0,0]},{"i":{"x":0.667,"y":1},"o":{"x":0.273,"y":0},"n":"0p667_1_0p273_0","t":50,"s":[1259.5,683,0],"e":[1161.5,791,0],"to":[0,0,0],"ti":[83,-36,0]},{"i":{"x":0.667,"y":1},"o":{"x":0.333,"y":0},"n":"0p667_1_0p333_0","t":117,"s":[1161.5,791,0],"e":[1270.5,867,0],"to":[43.5,62.5,0],"ti":[0,0,0]},{"i":{"x":0.667,"y":1},"o":{"x":0.333,"y":0},"n":"0p667_1_0p333_0","t":186,"s":[1270.5,867,0],"e":[1193.5,932,0],"to":[0,0,0],"ti":[60.5,-14.5,0]},{"t":249}],"ix":2},"a":{"a":0,"k":[17.5,7,0],"ix":1},"s":{"a":0,"k":[100,100,100],"ix":6}},"ao":0,"ip":31,"op":126,"st":-39,"bm":0},{"ddd":0,"ind":25,"ty":2,"nm":"叶子4","refId":"image_22","sr":1,"ks":{"o":{"a":1,"k":[{"i":{"x":[0.833],"y":[0.833]},"o":{"x":[0.167],"y":[0.167]},"n":["0p833_0p833_0p167_0p167"],"t":298,"s":[100],"e":[0]},{"t":308}],"ix":11},"r":{"a":1,"k":[{"i":{"x":[0.833],"y":[0.833]},"o":{"x":[0.167],"y":[0.167]},"n":["0p833_0p833_0p167_0p167"],"t":50,"s":[26],"e":[-16]},{"i":{"x":[0.833],"y":[0.833]},"o":{"x":[0.167],"y":[0.167]},"n":["0p833_0p833_0p167_0p167"],"t":117,"s":[-16],"e":[29]},{"i":{"x":[0.833],"y":[0.833]},"o":{"x":[0.167],"y":[0.167]},"n":["0p833_0p833_0p167_0p167"],"t":186,"s":[29],"e":[1]},{"i":{"x":[0.833],"y":[0.833]},"o":{"x":[0.167],"y":[0.167]},"n":["0p833_0p833_0p167_0p167"],"t":249,"s":[1],"e":[14]},{"t":308}],"ix":10},"p":{"a":1,"k":[{"i":{"x":0,"y":1},"o":{"x":0.188,"y":0},"n":"0_1_0p188_0","t":31,"s":[946.5,703,0],"e":[640.5,659,0],"to":[-51,-7.33333349227905,0],"ti":[0,0,0]},{"i":{"x":0.667,"y":1},"o":{"x":0.292,"y":0},"n":"0p667_1_0p292_0","t":50,"s":[640.5,659,0],"e":[716.5,768,0],"to":[0,0,0],"ti":[-69,-45.5,0]},{"i":{"x":0.667,"y":1},"o":{"x":0.333,"y":0},"n":"0p667_1_0p333_0","t":117,"s":[716.5,768,0],"e":[617.5,821,0],"to":[-36.5,53,0],"ti":[0,0,0]},{"i":{"x":0.667,"y":1},"o":{"x":0.333,"y":0},"n":"0p667_1_0p333_0","t":186,"s":[617.5,821,0],"e":[700.5,904,0],"to":[0,0,0],"ti":[-77,-36,0]},{"i":{"x":0.667,"y":1},"o":{"x":0.333,"y":0},"n":"0p667_1_0p333_0","t":249,"s":[700.5,904,0],"e":[609.5,980,0],"to":[-47,66.5,0],"ti":[0,0,0]},{"t":308}],"ix":2},"a":{"a":0,"k":[16.5,6,0],"ix":1},"s":{"a":0,"k":[100,100,100],"ix":6}},"ao":0,"ip":31,"op":126,"st":-39,"bm":0},{"ddd":0,"ind":27,"ty":2,"nm":"合成 2 (0-00-02-19).png","cl":"png","refId":"image_23","sr":1,"ks":{"o":{"a":0,"k":37,"ix":11},"r":{"a":1,"k":[{"i":{"x":[0.833],"y":[0.833]},"o":{"x":[0.167],"y":[0.167]},"n":["0p833_0p833_0p167_0p167"],"t":31,"s":[0],"e":[180]},{"t":312}],"ix":10},"p":{"a":0,"k":[946,677,0],"ix":2},"a":{"a":0,"k":[250,250,0],"ix":1},"s":{"a":1,"k":[{"i":{"x":[0.4,0.4,0.4],"y":[1,1,1]},"o":{"x":[0.7,0.7,0.7],"y":[0,0,0]},"n":["0p4_1_0p7_0","0p4_1_0p7_0","0p4_1_0p7_0"],"t":31,"s":[0,0,100],"e":[133.006,133.006,100]},{"i":{"x":[0.6,0.6,0.6],"y":[1,1,1]},"o":{"x":[0.4,0.4,0.4],"y":[0,0,0]},"n":["0p6_1_0p4_0","0p6_1_0p4_0","0p6_1_0p4_0"],"t":36.589,"s":[133.006,133.006,100],"e":[116.004,116.004,100]},{"i":{"x":[0.6,0.6,0.6],"y":[1,1,1]},"o":{"x":[0.4,0.4,0.4],"y":[0,0,0]},"n":["0p6_1_0p4_0","0p6_1_0p4_0","0p6_1_0p4_0"],"t":44.041,"s":[116.004,116.004,100],"e":[118.894,118.894,100]},{"i":{"x":[0.6,0.6,0.6],"y":[1,1,1]},"o":{"x":[0.4,0.4,0.4],"y":[0,0,0]},"n":["0p6_1_0p4_0","0p6_1_0p4_0","0p6_1_0p4_0"],"t":52.06,"s":[118.894,118.894,100],"e":[117.6,117.6,100]},{"t":58}],"ix":6}},"ao":0,"ip":31,"op":126,"st":31,"bm":0},{"ddd":0,"ind":28,"ty":2,"nm":"背景光2","refId":"image_24","sr":1,"ks":{"o":{"a":0,"k":100,"ix":11},"r":{"a":1,"k":[{"i":{"x":[0.833],"y":[0.833]},"o":{"x":[0.167],"y":[0.167]},"n":["0p833_0p833_0p167_0p167"],"t":31,"s":[-16],"e":[21]},{"t":312}],"ix":10},"p":{"a":0,"k":[878,609,0],"ix":2},"a":{"a":0,"k":[456,429,0],"ix":1},"s":{"a":1,"k":[{"i":{"x":[0.4,0.4,0.4],"y":[1,1,1]},"o":{"x":[0.7,0.7,0.7],"y":[0,0,0]},"n":["0p4_1_0p7_0","0p4_1_0p7_0","0p4_1_0p7_0"],"t":31,"s":[0,0,100],"e":[113.1,113.1,100]},{"i":{"x":[0.6,0.6,0.6],"y":[1,1,1]},"o":{"x":[0.4,0.4,0.4],"y":[0,0,0]},"n":["0p6_1_0p4_0","0p6_1_0p4_0","0p6_1_0p4_0"],"t":36.589,"s":[113.1,113.1,100],"e":[98.643,98.643,100]},{"i":{"x":[0.6,0.6,0.6],"y":[1,1,1]},"o":{"x":[0.4,0.4,0.4],"y":[0,0,0]},"n":["0p6_1_0p4_0","0p6_1_0p4_0","0p6_1_0p4_0"],"t":44.041,"s":[98.643,98.643,100],"e":[101.1,101.1,100]},{"i":{"x":[0.6,0.6,0.6],"y":[1,1,1]},"o":{"x":[0.4,0.4,0.4],"y":[0,0,0]},"n":["0p6_1_0p4_0","0p6_1_0p4_0","0p6_1_0p4_0"],"t":52.06,"s":[101.1,101.1,100],"e":[100,100,100]},{"t":58}],"ix":6}},"ao":0,"ip":0,"op":126,"st":-39,"bm":0}],"markers":[]}